{
  "timestamp": "2026-01-12T10:26:19.566323",
  "account": {
    "equity": 100791.67,
    "cash": 7545.66,
    "buying_power": 174649.14,
    "portfolio_value": 100791.67,
    "last_equity": 100486.9603265127,
    "daytrade_count": 26,
    "status": "ACTIVE",
    "pattern_day_trader": true
  },
  "positions": [
    {
      "symbol": "ASTI",
      "qty": 297.319247407,
      "avg_entry_price": 4.27,
      "current_price": 4.214,
      "market_value": 1252.903309,
      "cost_basis": 1269.553186,
      "unrealized_pl": -16.649877,
      "unrealized_plpc": -0.0131147534294794,
      "unrealized_intraday_pl": -16.649877,
      "unrealized_intraday_plpc": -0.0131147534294794
    },
    {
      "symbol": "ASTS",
      "qty": 8.496989777,
      "avg_entry_price": 95.33,
      "current_price": 95.03,
      "market_value": 807.468939,
      "cost_basis": 810.018035,
      "unrealized_pl": -2.549096,
      "unrealized_plpc": -0.003146962030296,
      "unrealized_intraday_pl": -2.549096,
      "unrealized_intraday_plpc": -0.003146962030296
    },
    {
      "symbol": "BIOA",
      "qty": 134.121117921,
      "avg_entry_price": 16.43,
      "current_price": 16.61,
      "market_value": 2227.751769,
      "cost_basis": 2203.609967,
      "unrealized_pl": 24.141802,
      "unrealized_plpc": 0.0109555694344888,
      "unrealized_intraday_pl": 24.141802,
      "unrealized_intraday_plpc": 0.0109555694344888
    },
    {
      "symbol": "COPX",
      "qty": 117.833749424,
      "avg_entry_price": 79.37,
      "current_price": 79.505,
      "market_value": 9368.372248,
      "cost_basis": 9352.464692,
      "unrealized_pl": 15.907556,
      "unrealized_plpc": 0.0017008945260822,
      "unrealized_intraday_pl": 15.907556,
      "unrealized_intraday_plpc": 0.0017008945260822
    },
    {
      "symbol": "GDX",
      "qty": 88.369596557,
      "avg_entry_price": 96.136539,
      "current_price": 96.9345,
      "market_value": 8566.062657,
      "cost_basis": 8495.547184,
      "unrealized_pl": 70.515473,
      "unrealized_plpc": 0.0083002861937845,
      "unrealized_intraday_pl": 70.515491,
      "unrealized_intraday_plpc": 0.0083002883301278
    },
    {
      "symbol": "GDXJ",
      "qty": 70.377835814,
      "avg_entry_price": 126.845597,
      "current_price": 128.09,
      "market_value": 9014.696989,
      "cost_basis": 8927.118596,
      "unrealized_pl": 87.578393,
      "unrealized_plpc": 0.0098103763334388,
      "unrealized_intraday_pl": 87.57839,
      "unrealized_intraday_plpc": 0.0098103759940873
    },
    {
      "symbol": "GDXU",
      "qty": 5.913575577,
      "avg_entry_price": 341.337056,
      "current_price": 342.1,
      "market_value": 2023.034205,
      "cost_basis": 2018.52248,
      "unrealized_pl": 4.511725,
      "unrealized_plpc": 0.002235162127102,
      "unrealized_intraday_pl": 4.511727,
      "unrealized_intraday_plpc": 0.0022351631201404
    },
    {
      "symbol": "GLD",
      "qty": 18.603782571,
      "avg_entry_price": 424.61,
      "current_price": 424.9,
      "market_value": 7904.747214,
      "cost_basis": 7899.352117,
      "unrealized_pl": 5.395097,
      "unrealized_plpc": 0.0006829796823956,
      "unrealized_intraday_pl": 5.395097,
      "unrealized_intraday_plpc": 0.0006829796823956
    },
    {
      "symbol": "KOLD",
      "qty": 98.981045254,
      "avg_entry_price": 46.41,
      "current_price": 46.2,
      "market_value": 4572.924291,
      "cost_basis": 4593.71031,
      "unrealized_pl": -20.786019,
      "unrealized_plpc": -0.0045248867684911,
      "unrealized_intraday_pl": -20.786019,
      "unrealized_intraday_plpc": -0.0045248867684911
    },
    {
      "symbol": "OSS",
      "qty": 125.096147869,
      "avg_entry_price": 9.14,
      "current_price": 9.06,
      "market_value": 1133.3711,
      "cost_basis": 1143.378792,
      "unrealized_pl": -10.007692,
      "unrealized_plpc": -0.0087527353752071,
      "unrealized_intraday_pl": -10.007692,
      "unrealized_intraday_plpc": -0.0087527353752071
    },
    {
      "symbol": "PICK",
      "qty": 178.145149101,
      "avg_entry_price": 55.22,
      "current_price": 55.27,
      "market_value": 9846.082391,
      "cost_basis": 9837.175133,
      "unrealized_pl": 8.907258,
      "unrealized_plpc": 0.000905469088389,
      "unrealized_intraday_pl": 8.907258,
      "unrealized_intraday_plpc": 0.000905469088389
    },
    {
      "symbol": "PPLT",
      "qty": 34.515016806,
      "avg_entry_price": 211.85,
      "current_price": 212.13,
      "market_value": 7321.670515,
      "cost_basis": 7312.00631,
      "unrealized_pl": 9.664205,
      "unrealized_plpc": 0.0013216899152266,
      "unrealized_intraday_pl": 9.664205,
      "unrealized_intraday_plpc": 0.0013216899152266
    },
    {
      "symbol": "SILJ",
      "qty": 288.376909148,
      "avg_entry_price": 32.201108,
      "current_price": 32.41,
      "market_value": 9346.295625,
      "cost_basis": 9286.056139,
      "unrealized_pl": 60.239486,
      "unrealized_plpc": 0.0064870904395035,
      "unrealized_intraday_pl": 60.239629,
      "unrealized_intraday_plpc": 0.0064871059388344
    },
    {
      "symbol": "SLV",
      "qty": 144.80741473,
      "avg_entry_price": 76.956961,
      "current_price": 77.53,
      "market_value": 11226.918864,
      "cost_basis": 11143.938546,
      "unrealized_pl": 82.980318,
      "unrealized_plpc": 0.0074462289663097,
      "unrealized_intraday_pl": 82.980296,
      "unrealized_intraday_plpc": 0.0074462269774422
    },
    {
      "symbol": "XME",
      "qty": 72.387914084,
      "avg_entry_price": 119.16,
      "current_price": 119.27,
      "market_value": 8633.706513,
      "cost_basis": 8625.743842,
      "unrealized_pl": 7.962671,
      "unrealized_plpc": 0.0009231286189173,
      "unrealized_intraday_pl": 7.962671,
      "unrealized_intraday_plpc": 0.0009231286189173
    }
  ],
  "scanner": {
    "timestamp": "2026-01-12T10:25:21.473059",
    "market_regime": "RISK_ON",
    "top_scorers": [
      {
        "ticker": "FBRX",
        "momentum": 100,
        "volatility": 56.14,
        "relative_strength": 100,
        "breakout": 99.87,
        "volume": 38.77,
        "rsi": 49.96,
        "composite": 87.28,
        "price": 29.67,
        "return_30d": 59.86,
        "is_overbought": 0,
        "is_oversold": 0,
        "has_loss_penalty": 0
      },
      {
        "ticker": "OSS",
        "momentum": 100,
        "volatility": 35.66,
        "relative_strength": 100,
        "breakout": 100,
        "volume": 63.22,
        "rsi": 65.72,
        "composite": 86.67,
        "price": 9.13,
        "return_30d": 49.92,
        "is_overbought": 0,
        "is_oversold": 0,
        "has_loss_penalty": 0
      },
      {
        "ticker": "RKLX",
        "momentum": 100,
        "volatility": 65.34,
        "relative_strength": 100,
        "breakout": 100,
        "volume": 15.97,
        "rsi": 60.61,
        "composite": 86.4,
        "price": 59.41,
        "return_30d": 216.12,
        "is_overbought": 0,
        "is_oversold": 0,
        "has_loss_penalty": 0
      },
      {
        "ticker": "ASTI",
        "momentum": 100,
        "volatility": 100,
        "relative_strength": 100,
        "breakout": 63.89,
        "volume": 4.54,
        "rsi": 50.68,
        "composite": 85.04,
        "price": 4.34,
        "return_30d": 164.33,
        "is_overbought": 0,
        "is_oversold": 0,
        "has_loss_penalty": 0
      },
      {
        "ticker": "GLSI",
        "momentum": 100,
        "volatility": 70.88,
        "relative_strength": 100,
        "breakout": 89.48,
        "volume": 4.24,
        "rsi": 67.81,
        "composite": 84.48,
        "price": 23.95,
        "return_30d": 174.34,
        "is_overbought": 0,
        "is_oversold": 0,
        "has_loss_penalty": 0
      },
      {
        "ticker": "CLYM",
        "momentum": 100,
        "volatility": 62.22,
        "relative_strength": 100,
        "breakout": 92.84,
        "volume": 4.11,
        "rsi": 56.61,
        "composite": 83.67,
        "price": 4.85,
        "return_30d": 156.61,
        "is_overbought": 0,
        "is_oversold": 0,
        "has_loss_penalty": 0
      },
      {
        "ticker": "BIOA",
        "momentum": 100,
        "volatility": 31.4,
        "relative_strength": 100,
        "breakout": 100,
        "volume": 34.21,
        "rsi": 64.42,
        "composite": 83.13,
        "price": 16.08,
        "return_30d": 69.44,
        "is_overbought": 0,
        "is_oversold": 0,
        "has_loss_penalty": 0
      },
      {
        "ticker": "FLYT",
        "momentum": 100,
        "volatility": 73.58,
        "relative_strength": 100,
        "breakout": 64.27,
        "volume": 23.14,
        "rsi": 59.14,
        "composite": 82.99,
        "price": 22.42,
        "return_30d": 127.02,
        "is_overbought": 0,
        "is_oversold": 0,
        "has_loss_penalty": 0
      },
      {
        "ticker": "ASTS",
        "momentum": 100,
        "volatility": 43.26,
        "relative_strength": 100,
        "breakout": 100,
        "volume": 12.09,
        "rsi": 63.74,
        "composite": 82.7,
        "price": 97.69,
        "return_30d": 73.83,
        "is_overbought": 0,
        "is_oversold": 0,
        "has_loss_penalty": 0
      },
      {
        "ticker": "GDXU",
        "momentum": 100,
        "volatility": 34.35,
        "relative_strength": 100,
        "breakout": 100,
        "volume": 19.99,
        "rsi": 65.91,
        "composite": 82.15,
        "price": 335.5,
        "return_30d": 49.89,
        "is_overbought": 0,
        "is_oversold": 0,
        "has_loss_penalty": 0
      }
    ],
    "total_tickers_scored": 5275
  }
}