{
  "timestamp": "2026-01-13T11:15:19.493714",
  "account": {
    "equity": 100600.12,
    "cash": -6.12,
    "buying_power": 273137.47,
    "portfolio_value": 100600.12,
    "last_equity": 100773.08154475834,
    "daytrade_count": 68,
    "status": "ACTIVE",
    "pattern_day_trader": true
  },
  "positions": [
    {
      "symbol": "QQQ",
      "qty": 60.404271091,
      "avg_entry_price": 627.707284,
      "current_price": 626.22,
      "market_value": 37826.362643,
      "cost_basis": 37916.20093,
      "unrealized_pl": -89.838287,
      "unrealized_plpc": -0.0023693905189989,
      "unrealized_intraday_pl": -57.384057,
      "unrealized_intraday_plpc": -0.0015147408057187
    },
    {
      "symbol": "SPY",
      "qty": 90.468735914,
      "avg_entry_price": 694.349771,
      "current_price": 693.94,
      "market_value": 62779.8746,
      "cost_basis": 62816.946097,
      "unrealized_pl": -37.071497,
      "unrealized_plpc": -0.0005901512140172,
      "unrealized_intraday_pl": -110.371858,
      "unrealized_intraday_plpc": -0.0017549916595367
    }
  ],
  "scanner": {
    "timestamp": "2026-01-13T11:14:02.372237",
    "market_regime": "RISK_ON",
    "top_scorers": [
      {
        "ticker": "ASTI",
        "momentum": 100,
        "volatility": 100,
        "relative_strength": 100,
        "breakout": 90.55,
        "volume": 16.59,
        "rsi": 57.53,
        "composite": 90.24,
        "price": 5.04,
        "return_30d": 218.99,
        "is_overbought": 0,
        "is_oversold": 0,
        "has_loss_penalty": 0
      },
      {
        "ticker": "FLNT",
        "momentum": 100,
        "volatility": 40.37,
        "relative_strength": 100,
        "breakout": 100,
        "volume": 100,
        "rsi": 71.22,
        "composite": 89.95,
        "price": 3.52,
        "return_30d": 100.0,
        "is_overbought": 1,
        "is_oversold": 0,
        "has_loss_penalty": 0
      },
      {
        "ticker": "FBIO",
        "momentum": 100,
        "volatility": 36.08,
        "relative_strength": 100,
        "breakout": 76.48,
        "volume": 100,
        "rsi": 56.98,
        "composite": 86.88,
        "price": 3.86,
        "return_30d": 42.1,
        "is_overbought": 0,
        "is_oversold": 0,
        "has_loss_penalty": 0
      },
      {
        "ticker": "RKLX",
        "momentum": 100,
        "volatility": 63.79,
        "relative_strength": 100,
        "breakout": 96.92,
        "volume": 21.3,
        "rsi": 53.65,
        "composite": 86.24,
        "price": 60.8,
        "return_30d": 253.35,
        "is_overbought": 0,
        "is_oversold": 0,
        "has_loss_penalty": 0
      },
      {
        "ticker": "VELO",
        "momentum": 100,
        "volatility": 64.13,
        "relative_strength": 100,
        "breakout": 91.13,
        "volume": 27.69,
        "rsi": 65.97,
        "composite": 86.06,
        "price": 21.11,
        "return_30d": 327.76,
        "is_overbought": 0,
        "is_oversold": 0,
        "has_loss_penalty": 0
      },
      {
        "ticker": "ORMP",
        "momentum": 100,
        "volatility": 22.36,
        "relative_strength": 100,
        "breakout": 100,
        "volume": 88.02,
        "rsi": 71.93,
        "composite": 85.47,
        "price": 3.58,
        "return_30d": 30.36,
        "is_overbought": 1,
        "is_oversold": 0,
        "has_loss_penalty": 0
      },
      {
        "ticker": "FBRX",
        "momentum": 100,
        "volatility": 54.81,
        "relative_strength": 100,
        "breakout": 100,
        "volume": 22.23,
        "rsi": 53.27,
        "composite": 85.44,
        "price": 30.96,
        "return_30d": 70.08,
        "is_overbought": 0,
        "is_oversold": 0,
        "has_loss_penalty": 0
      },
      {
        "ticker": "OSS",
        "momentum": 100,
        "volatility": 34.82,
        "relative_strength": 100,
        "breakout": 100,
        "volume": 100,
        "rsi": 75.66,
        "composite": 85.12,
        "price": 11.16,
        "return_30d": 88.51,
        "is_overbought": 1,
        "is_oversold": 0,
        "has_loss_penalty": 0
      },
      {
        "ticker": "TE",
        "momentum": 100,
        "volatility": 45.51,
        "relative_strength": 100,
        "breakout": 94.88,
        "volume": 26.01,
        "rsi": 56.6,
        "composite": 83.66,
        "price": 7.99,
        "return_30d": 78.75,
        "is_overbought": 0,
        "is_oversold": 0,
        "has_loss_penalty": 0
      },
      {
        "ticker": "HYMC",
        "momentum": 100,
        "volatility": 40.75,
        "relative_strength": 100,
        "breakout": 100,
        "volume": 26.78,
        "rsi": 70.51,
        "composite": 83.36,
        "price": 34.94,
        "return_30d": 195.85,
        "is_overbought": 1,
        "is_oversold": 0,
        "has_loss_penalty": 0
      }
    ],
    "total_tickers_scored": 5274
  }
}