{
  "timestamp": "2026-01-21T14:59:56.599962",
  "account": {
    "equity": 95492.66,
    "cash": -14740.12,
    "buying_power": 212040.77,
    "portfolio_value": 95492.66,
    "last_equity": 95933.64557895635,
    "daytrade_count": 136,
    "status": "ACTIVE",
    "pattern_day_trader": true
  },
  "positions": [
    {
      "symbol": "COPX",
      "qty": 139.86133151,
      "avg_entry_price": 81.073192,
      "current_price": 83.88,
      "market_value": 11731.568487,
      "cost_basis": 11339.004583,
      "unrealized_pl": 392.563904,
      "unrealized_plpc": 0.034620667195827,
      "unrealized_intraday_pl": 227.97397,
      "unrealized_intraday_plpc": 0.0198176291474026
    },
    {
      "symbol": "GDX",
      "qty": 129.159399016,
      "avg_entry_price": 98.684572,
      "current_price": 101.14,
      "market_value": 13063.181616,
      "cost_basis": 12746.040012,
      "unrealized_pl": 317.141604,
      "unrealized_plpc": 0.0248815791964737,
      "unrealized_intraday_pl": -211.821415,
      "unrealized_intraday_plpc": -0.0159564117993308
    },
    {
      "symbol": "PICK",
      "qty": 315.520299417,
      "avg_entry_price": 56.214351,
      "current_price": 58.16,
      "market_value": 18350.660614,
      "cost_basis": 17736.768859,
      "unrealized_pl": 613.891755,
      "unrealized_plpc": 0.0346112507796762,
      "unrealized_intraday_pl": 492.211667,
      "unrealized_intraday_plpc": 0.027561837450765
    },
    {
      "symbol": "PPLT",
      "qty": 8.439378948,
      "avg_entry_price": 209.773145,
      "current_price": 225.42,
      "market_value": 1902.404802,
      "cost_basis": 1770.355064,
      "unrealized_pl": 132.049738,
      "unrealized_plpc": 0.0745894090316789,
      "unrealized_intraday_pl": 11.393161,
      "unrealized_intraday_plpc": 0.0060249026251235
    },
    {
      "symbol": "REMX",
      "qty": 184.895902271,
      "avg_entry_price": 89.138119,
      "current_price": 92.14,
      "market_value": 17036.308435,
      "cost_basis": 16481.272939,
      "unrealized_pl": 555.035496,
      "unrealized_plpc": 0.0336767371097051,
      "unrealized_intraday_pl": 486.276223,
      "unrealized_intraday_plpc": 0.029382191936002
    },
    {
      "symbol": "SILJ",
      "qty": 433.07914685,
      "avg_entry_price": 33.809719,
      "current_price": 34.745,
      "market_value": 15047.334957,
      "cost_basis": 14642.28426,
      "unrealized_pl": 405.050697,
      "unrealized_plpc": 0.0276630811018007,
      "unrealized_intraday_pl": -257.682093,
      "unrealized_intraday_plpc": -0.0168364459940278
    },
    {
      "symbol": "SLV",
      "qty": 142.064239172,
      "avg_entry_price": 81.541493,
      "current_price": 82.8199,
      "market_value": 11765.746082,
      "cost_basis": 11584.130164,
      "unrealized_pl": 181.615918,
      "unrealized_plpc": 0.0156779935505566,
      "unrealized_intraday_pl": -365.119301,
      "unrealized_intraday_plpc": -0.0300983721665622
    },
    {
      "symbol": "TE",
      "qty": 12.29190046,
      "avg_entry_price": 8.15,
      "current_price": 7.9099,
      "market_value": 97.227703,
      "cost_basis": 100.178989,
      "unrealized_pl": -2.951286,
      "unrealized_plpc": -0.0294601296086148,
      "unrealized_intraday_pl": -4.549233,
      "unrealized_intraday_plpc": -0.0446980738347242
    },
    {
      "symbol": "VELO",
      "qty": 38.729690548,
      "avg_entry_price": 21.36,
      "current_price": 17.3424,
      "market_value": 671.665785,
      "cost_basis": 827.26619,
      "unrealized_pl": -155.600405,
      "unrealized_plpc": -0.188089887971851,
      "unrealized_intraday_pl": -71.556977,
      "unrealized_intraday_plpc": -0.096279313092405
    },
    {
      "symbol": "XME",
      "qty": 161.231432643,
      "avg_entry_price": 124.304824,
      "current_price": 127.56,
      "market_value": 20566.681548,
      "cost_basis": 20041.844858,
      "unrealized_pl": 524.83669,
      "unrealized_plpc": 0.0261870448413587,
      "unrealized_intraday_pl": 285.379636,
      "unrealized_intraday_plpc": 0.0140710708433933
    }
  ],
  "scanner": {
    "timestamp": "2026-01-20T20:11:55.416006",
    "market_regime": "RISK_OFF",
    "top_scorers": [
      {
        "ticker": "SHMDW",
        "momentum": 100,
        "volatility": 81.6,
        "relative_strength": 100,
        "breakout": 95.14,
        "volume": 100,
        "rsi": 70.35,
        "composite": 96.17,
        "price": 2.81,
        "return_30d": 219.32,
        "is_overbought": 1,
        "is_oversold": 0,
        "has_loss_penalty": 0
      },
      {
        "ticker": "TE",
        "momentum": 100,
        "volatility": 50.46,
        "relative_strength": 100,
        "breakout": 100,
        "volume": 84.82,
        "rsi": 66.79,
        "composite": 91.05,
        "price": 8.28,
        "return_30d": 42.02,
        "is_overbought": 0,
        "is_oversold": 0,
        "has_loss_penalty": 0
      },
      {
        "ticker": "CNTX",
        "momentum": 100,
        "volatility": 54.42,
        "relative_strength": 100,
        "breakout": 85.54,
        "volume": 100,
        "rsi": 67.37,
        "composite": 90.99,
        "price": 1.54,
        "return_30d": 46.67,
        "is_overbought": 0,
        "is_oversold": 0,
        "has_loss_penalty": 0
      },
      {
        "ticker": "SHMD",
        "momentum": 100,
        "volatility": 49.95,
        "relative_strength": 100,
        "breakout": 100,
        "volume": 100,
        "rsi": 72.35,
        "composite": 90.32,
        "price": 9.19,
        "return_30d": 96.79,
        "is_overbought": 1,
        "is_oversold": 0,
        "has_loss_penalty": 0
      },
      {
        "ticker": "MRKR",
        "momentum": 100,
        "volatility": 44.77,
        "relative_strength": 100,
        "breakout": 82.76,
        "volume": 100,
        "rsi": 66.85,
        "composite": 89.13,
        "price": 2.12,
        "return_30d": 60.61,
        "is_overbought": 0,
        "is_oversold": 0,
        "has_loss_penalty": 0
      },
      {
        "ticker": "OSS",
        "momentum": 100,
        "volatility": 43.38,
        "relative_strength": 100,
        "breakout": 84.43,
        "volume": 100,
        "rsi": 70.7,
        "composite": 88.55,
        "price": 10.78,
        "return_30d": 54.44,
        "is_overbought": 1,
        "is_oversold": 0,
        "has_loss_penalty": 0
      },
      {
        "ticker": "EDAP",
        "momentum": 100,
        "volatility": 42.75,
        "relative_strength": 100,
        "breakout": 80.0,
        "volume": 100,
        "rsi": 64.74,
        "composite": 88.41,
        "price": 3.69,
        "return_30d": 53.75,
        "is_overbought": 0,
        "is_oversold": 0,
        "has_loss_penalty": 0
      },
      {
        "ticker": "ASM",
        "momentum": 100,
        "volatility": 29.09,
        "relative_strength": 100,
        "breakout": 98.86,
        "volume": 92.06,
        "rsi": 58.47,
        "composite": 88.4,
        "price": 7.0,
        "return_30d": 27.5,
        "is_overbought": 0,
        "is_oversold": 0,
        "has_loss_penalty": 0
      },
      {
        "ticker": "IZM",
        "momentum": 100,
        "volatility": 100,
        "relative_strength": 100,
        "breakout": 3.68,
        "volume": 8.96,
        "rsi": 29.67,
        "composite": 87.91,
        "price": 1.41,
        "return_30d": 56.68,
        "is_overbought": 0,
        "is_oversold": 1,
        "has_loss_penalty": 0
      },
      {
        "ticker": "FLYT",
        "momentum": 100,
        "volatility": 85.41,
        "relative_strength": 100,
        "breakout": 64.15,
        "volume": 51.94,
        "rsi": 64.18,
        "composite": 87.63,
        "price": 23.35,
        "return_30d": 90.77,
        "is_overbought": 0,
        "is_oversold": 0,
        "has_loss_penalty": 0
      }
    ],
    "total_tickers_scored": 5285
  }
}