{
  "timestamp": "2026-01-21T14:37:36.364520",
  "account": {
    "equity": 95141.17,
    "cash": -14740.12,
    "buying_power": 212040.77,
    "portfolio_value": 95141.17,
    "last_equity": 95933.64557895635,
    "daytrade_count": 136,
    "status": "ACTIVE",
    "pattern_day_trader": true
  },
  "positions": [
    {
      "symbol": "COPX",
      "qty": 139.86133151,
      "avg_entry_price": 81.073192,
      "current_price": 83.48,
      "market_value": 11675.623954,
      "cost_basis": 11339.004583,
      "unrealized_pl": 336.619371,
      "unrealized_plpc": 0.0296868537741555,
      "unrealized_intraday_pl": 172.029437,
      "unrealized_intraday_plpc": 0.014954407228608
    },
    {
      "symbol": "GDX",
      "qty": 129.159399016,
      "avg_entry_price": 98.684572,
      "current_price": 101.22,
      "market_value": 13073.514368,
      "cost_basis": 12746.040012,
      "unrealized_pl": 327.474356,
      "unrealized_plpc": 0.0256922428998884,
      "unrealized_intraday_pl": -201.488663,
      "unrealized_intraday_plpc": -0.0151780502444693
    },
    {
      "symbol": "PICK",
      "qty": 315.520299417,
      "avg_entry_price": 56.214351,
      "current_price": 57.95,
      "market_value": 18284.401351,
      "cost_basis": 17736.768859,
      "unrealized_pl": 547.632492,
      "unrealized_plpc": 0.0308755499016451,
      "unrealized_intraday_pl": 425.952404,
      "unrealized_intraday_plpc": 0.0238515900940857
    },
    {
      "symbol": "PPLT",
      "qty": 8.439378948,
      "avg_entry_price": 209.773145,
      "current_price": 225.3988,
      "market_value": 1902.225888,
      "cost_basis": 1770.355064,
      "unrealized_pl": 131.870824,
      "unrealized_plpc": 0.0744883479487141,
      "unrealized_intraday_pl": 11.214247,
      "unrealized_intraday_plpc": 0.0059302897755139
    },
    {
      "symbol": "REMX",
      "qty": 184.895902271,
      "avg_entry_price": 89.138119,
      "current_price": 91.71,
      "market_value": 16956.803197,
      "cost_basis": 16481.272939,
      "unrealized_pl": 475.530258,
      "unrealized_plpc": 0.0288527627544316,
      "unrealized_intraday_pl": 406.770985,
      "unrealized_intraday_plpc": 0.0245782594129974
    },
    {
      "symbol": "SILJ",
      "qty": 433.07914685,
      "avg_entry_price": 33.809719,
      "current_price": 34.745,
      "market_value": 15047.334957,
      "cost_basis": 14642.28426,
      "unrealized_pl": 405.050697,
      "unrealized_plpc": 0.0276630811018007,
      "unrealized_intraday_pl": -257.682093,
      "unrealized_intraday_plpc": -0.0168364459940278
    },
    {
      "symbol": "SLV",
      "qty": 142.064239172,
      "avg_entry_price": 81.541493,
      "current_price": 82.57,
      "market_value": 11730.244228,
      "cost_basis": 11584.130164,
      "unrealized_pl": 146.114064,
      "unrealized_plpc": 0.0126132961155839,
      "unrealized_intraday_pl": -400.621155,
      "unrealized_intraday_plpc": -0.0330249444166963
    },
    {
      "symbol": "TE",
      "qty": 12.29190046,
      "avg_entry_price": 8.15,
      "current_price": 7.785,
      "market_value": 95.692445,
      "cost_basis": 100.178989,
      "unrealized_pl": -4.486544,
      "unrealized_plpc": -0.0447852792764758,
      "unrealized_intraday_pl": -6.084491,
      "unrealized_intraday_plpc": -0.0597826112588023
    },
    {
      "symbol": "VELO",
      "qty": 38.729690548,
      "avg_entry_price": 21.36,
      "current_price": 17.0,
      "market_value": 658.404739,
      "cost_basis": 827.26619,
      "unrealized_pl": -168.861451,
      "unrealized_plpc": -0.2041198504679612,
      "unrealized_intraday_pl": -84.818023,
      "unrealized_intraday_plpc": -0.1141219393923783
    },
    {
      "symbol": "XME",
      "qty": 161.231432643,
      "avg_entry_price": 124.304824,
      "current_price": 126.88,
      "market_value": 20457.044174,
      "cost_basis": 20041.844858,
      "unrealized_pl": 415.199316,
      "unrealized_plpc": 0.0207166215955547,
      "unrealized_intraday_pl": 175.742262,
      "unrealized_intraday_plpc": 0.0086652357310463
    }
  ],
  "scanner": {
    "timestamp": "2026-01-20T20:11:55.416006",
    "market_regime": "RISK_OFF",
    "top_scorers": [
      {
        "ticker": "SHMDW",
        "momentum": 100,
        "volatility": 81.6,
        "relative_strength": 100,
        "breakout": 95.14,
        "volume": 100,
        "rsi": 70.35,
        "composite": 96.17,
        "price": 2.81,
        "return_30d": 219.32,
        "is_overbought": 1,
        "is_oversold": 0,
        "has_loss_penalty": 0
      },
      {
        "ticker": "TE",
        "momentum": 100,
        "volatility": 50.46,
        "relative_strength": 100,
        "breakout": 100,
        "volume": 84.82,
        "rsi": 66.79,
        "composite": 91.05,
        "price": 8.28,
        "return_30d": 42.02,
        "is_overbought": 0,
        "is_oversold": 0,
        "has_loss_penalty": 0
      },
      {
        "ticker": "CNTX",
        "momentum": 100,
        "volatility": 54.42,
        "relative_strength": 100,
        "breakout": 85.54,
        "volume": 100,
        "rsi": 67.37,
        "composite": 90.99,
        "price": 1.54,
        "return_30d": 46.67,
        "is_overbought": 0,
        "is_oversold": 0,
        "has_loss_penalty": 0
      },
      {
        "ticker": "SHMD",
        "momentum": 100,
        "volatility": 49.95,
        "relative_strength": 100,
        "breakout": 100,
        "volume": 100,
        "rsi": 72.35,
        "composite": 90.32,
        "price": 9.19,
        "return_30d": 96.79,
        "is_overbought": 1,
        "is_oversold": 0,
        "has_loss_penalty": 0
      },
      {
        "ticker": "MRKR",
        "momentum": 100,
        "volatility": 44.77,
        "relative_strength": 100,
        "breakout": 82.76,
        "volume": 100,
        "rsi": 66.85,
        "composite": 89.13,
        "price": 2.12,
        "return_30d": 60.61,
        "is_overbought": 0,
        "is_oversold": 0,
        "has_loss_penalty": 0
      },
      {
        "ticker": "OSS",
        "momentum": 100,
        "volatility": 43.38,
        "relative_strength": 100,
        "breakout": 84.43,
        "volume": 100,
        "rsi": 70.7,
        "composite": 88.55,
        "price": 10.78,
        "return_30d": 54.44,
        "is_overbought": 1,
        "is_oversold": 0,
        "has_loss_penalty": 0
      },
      {
        "ticker": "EDAP",
        "momentum": 100,
        "volatility": 42.75,
        "relative_strength": 100,
        "breakout": 80.0,
        "volume": 100,
        "rsi": 64.74,
        "composite": 88.41,
        "price": 3.69,
        "return_30d": 53.75,
        "is_overbought": 0,
        "is_oversold": 0,
        "has_loss_penalty": 0
      },
      {
        "ticker": "ASM",
        "momentum": 100,
        "volatility": 29.09,
        "relative_strength": 100,
        "breakout": 98.86,
        "volume": 92.06,
        "rsi": 58.47,
        "composite": 88.4,
        "price": 7.0,
        "return_30d": 27.5,
        "is_overbought": 0,
        "is_oversold": 0,
        "has_loss_penalty": 0
      },
      {
        "ticker": "IZM",
        "momentum": 100,
        "volatility": 100,
        "relative_strength": 100,
        "breakout": 3.68,
        "volume": 8.96,
        "rsi": 29.67,
        "composite": 87.91,
        "price": 1.41,
        "return_30d": 56.68,
        "is_overbought": 0,
        "is_oversold": 1,
        "has_loss_penalty": 0
      },
      {
        "ticker": "FLYT",
        "momentum": 100,
        "volatility": 85.41,
        "relative_strength": 100,
        "breakout": 64.15,
        "volume": 51.94,
        "rsi": 64.18,
        "composite": 87.63,
        "price": 23.35,
        "return_30d": 90.77,
        "is_overbought": 0,
        "is_oversold": 0,
        "has_loss_penalty": 0
      }
    ],
    "total_tickers_scored": 5285
  }
}