{
  "timestamp": "2026-01-12T10:55:54.125150",
  "account": {
    "equity": 100646.05,
    "cash": 9440.6,
    "buying_power": 175943.79,
    "portfolio_value": 100646.05,
    "last_equity": 100486.9603265127,
    "daytrade_count": 42,
    "status": "ACTIVE",
    "pattern_day_trader": true
  },
  "positions": [
    {
      "symbol": "ASTI",
      "qty": 305.246867351,
      "avg_entry_price": 4.44,
      "current_price": 4.3,
      "market_value": 1312.56153,
      "cost_basis": 1355.296091,
      "unrealized_pl": -42.734561,
      "unrealized_plpc": -0.0315315312157866,
      "unrealized_intraday_pl": -42.734561,
      "unrealized_intraday_plpc": -0.0315315312157866
    },
    {
      "symbol": "ASTS",
      "qty": 8.864644271,
      "avg_entry_price": 96.72,
      "current_price": 96.65,
      "market_value": 856.767869,
      "cost_basis": 857.388394,
      "unrealized_pl": -0.620525,
      "unrealized_plpc": -0.0007237385114406,
      "unrealized_intraday_pl": -0.620525,
      "unrealized_intraday_plpc": -0.0007237385114406
    },
    {
      "symbol": "BIOA",
      "qty": 134.997429285,
      "avg_entry_price": 16.99,
      "current_price": 16.78,
      "market_value": 2265.256863,
      "cost_basis": 2293.606324,
      "unrealized_pl": -28.349461,
      "unrealized_plpc": -0.012360212257594,
      "unrealized_intraday_pl": -28.349461,
      "unrealized_intraday_plpc": -0.012360212257594
    },
    {
      "symbol": "COPX",
      "qty": 122.614643931,
      "avg_entry_price": 79.401336,
      "current_price": 79.67,
      "market_value": 9768.708682,
      "cost_basis": 9735.766523,
      "unrealized_pl": 32.942159,
      "unrealized_plpc": 0.0033836225347205,
      "unrealized_intraday_pl": 32.942141,
      "unrealized_intraday_plpc": 0.0033836206796118
    },
    {
      "symbol": "CPER",
      "qty": 181.288156045,
      "avg_entry_price": 36.91,
      "current_price": 36.91,
      "market_value": 6691.34584,
      "cost_basis": 6691.34584,
      "unrealized_pl": 0.0,
      "unrealized_plpc": 0.0,
      "unrealized_intraday_pl": 0.0,
      "unrealized_intraday_plpc": 0.0
    },
    {
      "symbol": "GDX",
      "qty": 91.785128175,
      "avg_entry_price": 96.239389,
      "current_price": 96.39,
      "market_value": 8847.168505,
      "cost_basis": 8833.34464,
      "unrealized_pl": 13.823865,
      "unrealized_plpc": 0.0015649638459029,
      "unrealized_intraday_pl": 13.82385,
      "unrealized_intraday_plpc": 0.0015649621451344
    },
    {
      "symbol": "GDXJ",
      "qty": 73.049887238,
      "avg_entry_price": 127.018619,
      "current_price": 127.46,
      "market_value": 9310.938627,
      "cost_basis": 9278.69576,
      "unrealized_pl": 32.242867,
      "unrealized_plpc": 0.0034749352531848,
      "unrealized_intraday_pl": 32.242832,
      "unrealized_intraday_plpc": 0.0034749314679952
    },
    {
      "symbol": "GLD",
      "qty": 19.381255601,
      "avg_entry_price": 424.846511,
      "current_price": 424.68,
      "market_value": 8230.831629,
      "cost_basis": 8234.058817,
      "unrealized_pl": -3.227188,
      "unrealized_plpc": -0.000391931618625,
      "unrealized_intraday_pl": -3.227192,
      "unrealized_intraday_plpc": -0.0003919321042217
    },
    {
      "symbol": "KOLD",
      "qty": 102.728757061,
      "avg_entry_price": 46.389727,
      "current_price": 45.88,
      "market_value": 4713.195374,
      "cost_basis": 4765.558974,
      "unrealized_pl": -52.3636,
      "unrealized_plpc": -0.0109879240369673,
      "unrealized_intraday_pl": -52.363621,
      "unrealized_intraday_plpc": -0.0109879283951662
    },
    {
      "symbol": "OSS",
      "qty": 127.508556651,
      "avg_entry_price": 9.19,
      "current_price": 9.246,
      "market_value": 1178.944115,
      "cost_basis": 1171.803636,
      "unrealized_pl": 7.140479,
      "unrealized_plpc": 0.0060935798291037,
      "unrealized_intraday_pl": 7.140479,
      "unrealized_intraday_plpc": 0.0060935798291037
    },
    {
      "symbol": "PPLT",
      "qty": 36.042850775,
      "avg_entry_price": 212.079899,
      "current_price": 213.32,
      "market_value": 7688.660927,
      "cost_basis": 7643.964149,
      "unrealized_pl": 44.696778,
      "unrealized_plpc": 0.0058473296222677,
      "unrealized_intraday_pl": 44.696775,
      "unrealized_intraday_plpc": 0.0058473292275063
    },
    {
      "symbol": "SILJ",
      "qty": 299.110235418,
      "avg_entry_price": 32.223929,
      "current_price": 32.25,
      "market_value": 9646.305092,
      "cost_basis": 9638.507028,
      "unrealized_pl": 7.798064,
      "unrealized_plpc": 0.0008090531009986,
      "unrealized_intraday_pl": 7.798103,
      "unrealized_intraday_plpc": 0.0008090571505421
    },
    {
      "symbol": "SLV",
      "qty": 150.079640909,
      "avg_entry_price": 77.04597,
      "current_price": 77.41,
      "market_value": 11617.665003,
      "cost_basis": 11563.031451,
      "unrealized_pl": 54.633552,
      "unrealized_plpc": 0.004724846787066,
      "unrealized_intraday_pl": 54.633492,
      "unrealized_intraday_plpc": 0.0047248415735983
    },
    {
      "symbol": "XME",
      "qty": 75.825750132,
      "avg_entry_price": 119.193724,
      "current_price": 119.71,
      "market_value": 9077.100548,
      "cost_basis": 9037.95355,
      "unrealized_pl": 39.146998,
      "unrealized_plpc": 0.0043314006631512,
      "unrealized_intraday_pl": 39.147015,
      "unrealized_intraday_plpc": 0.0043314025522552
    }
  ],
  "scanner": {
    "timestamp": "2026-01-12T10:53:37.374164",
    "market_regime": "RISK_ON",
    "top_scorers": [
      {
        "ticker": "FBRX",
        "momentum": 100,
        "volatility": 57.27,
        "relative_strength": 100,
        "breakout": 98.35,
        "volume": 67.17,
        "rsi": 49.48,
        "composite": 90.06,
        "price": 29.44,
        "return_30d": 58.65,
        "is_overbought": 0,
        "is_oversold": 0,
        "has_loss_penalty": 0
      },
      {
        "ticker": "OSS",
        "momentum": 100,
        "volatility": 36.79,
        "relative_strength": 100,
        "breakout": 100,
        "volume": 85.3,
        "rsi": 63.94,
        "composite": 89.05,
        "price": 8.85,
        "return_30d": 45.32,
        "is_overbought": 0,
        "is_oversold": 0,
        "has_loss_penalty": 0
      },
      {
        "ticker": "RKLX",
        "momentum": 100,
        "volatility": 67.72,
        "relative_strength": 100,
        "breakout": 94.71,
        "volume": 24.24,
        "rsi": 59.44,
        "composite": 86.79,
        "price": 57.82,
        "return_30d": 207.66,
        "is_overbought": 0,
        "is_oversold": 0,
        "has_loss_penalty": 0
      },
      {
        "ticker": "ASTI",
        "momentum": 100,
        "volatility": 100,
        "relative_strength": 100,
        "breakout": 64.46,
        "volume": 7.88,
        "rsi": 50.78,
        "composite": 85.46,
        "price": 4.35,
        "return_30d": 165.24,
        "is_overbought": 0,
        "is_oversold": 0,
        "has_loss_penalty": 0
      },
      {
        "ticker": "GLSI",
        "momentum": 100,
        "volatility": 73.82,
        "relative_strength": 100,
        "breakout": 83.62,
        "volume": 6.83,
        "rsi": 66.21,
        "composite": 84.3,
        "price": 23.21,
        "return_30d": 165.86,
        "is_overbought": 0,
        "is_oversold": 0,
        "has_loss_penalty": 0
      },
      {
        "ticker": "BIOA",
        "momentum": 100,
        "volatility": 30.66,
        "relative_strength": 100,
        "breakout": 100,
        "volume": 45.35,
        "rsi": 65.84,
        "composite": 84.13,
        "price": 16.47,
        "return_30d": 73.55,
        "is_overbought": 0,
        "is_oversold": 0,
        "has_loss_penalty": 0
      },
      {
        "ticker": "FLYT",
        "momentum": 100,
        "volatility": 76.24,
        "relative_strength": 100,
        "breakout": 60.46,
        "volume": 31.3,
        "rsi": 58.1,
        "composite": 83.63,
        "price": 21.9,
        "return_30d": 121.76,
        "is_overbought": 0,
        "is_oversold": 0,
        "has_loss_penalty": 0
      },
      {
        "ticker": "CLYM",
        "momentum": 100,
        "volatility": 64.64,
        "relative_strength": 100,
        "breakout": 88.0,
        "volume": 7.26,
        "rsi": 55.06,
        "composite": 83.62,
        "price": 4.73,
        "return_30d": 150.17,
        "is_overbought": 0,
        "is_oversold": 0,
        "has_loss_penalty": 0
      },
      {
        "ticker": "DBGI",
        "momentum": 100,
        "volatility": 53.81,
        "relative_strength": 100,
        "breakout": 78.05,
        "volume": 40.1,
        "rsi": 70.62,
        "composite": 83.27,
        "price": 15.25,
        "return_30d": 110.64,
        "is_overbought": 1,
        "is_oversold": 0,
        "has_loss_penalty": 0
      },
      {
        "ticker": "ASTS",
        "momentum": 100,
        "volatility": 44.24,
        "relative_strength": 100,
        "breakout": 95.62,
        "volume": 19.52,
        "rsi": 62.07,
        "composite": 82.93,
        "price": 95.53,
        "return_30d": 69.99,
        "is_overbought": 0,
        "is_oversold": 0,
        "has_loss_penalty": 0
      }
    ],
    "total_tickers_scored": 5275
  }
}