{
  "timestamp": "2026-01-14T12:49:42.162870",
  "account": {
    "equity": 98720.83,
    "cash": 190.74,
    "buying_power": 127960.64,
    "portfolio_value": 98720.83,
    "last_equity": 100251.4951397331,
    "daytrade_count": 137,
    "status": "ACTIVE",
    "pattern_day_trader": true
  },
  "positions": [
    {
      "symbol": "COPX",
      "qty": 123.519353017,
      "avg_entry_price": 81.890333,
      "current_price": 81.7,
      "market_value": 10091.531141,
      "cost_basis": 10115.04094,
      "unrealized_pl": -23.509799,
      "unrealized_plpc": -0.0023242416060849,
      "unrealized_intraday_pl": -23.50981,
      "unrealized_intraday_plpc": -0.0023242426910467
    },
    {
      "symbol": "CPER",
      "qty": 201.523431832,
      "avg_entry_price": 37.102777,
      "current_price": 37.17,
      "market_value": 7490.625961,
      "cost_basis": 7477.078893,
      "unrealized_pl": 13.547068,
      "unrealized_plpc": 0.0018118129009823,
      "unrealized_intraday_pl": 13.547009,
      "unrealized_intraday_plpc": 0.0018118049959037
    },
    {
      "symbol": "KOLD",
      "qty": 107.451003239,
      "avg_entry_price": 45.447675,
      "current_price": 46.14,
      "market_value": 4957.789289,
      "cost_basis": 4883.39823,
      "unrealized_pl": 74.391059,
      "unrealized_plpc": 0.0152334615151794,
      "unrealized_intraday_pl": 74.391015,
      "unrealized_intraday_plpc": 0.015233452367805
    },
    {
      "symbol": "PICK",
      "qty": 238.189409473,
      "avg_entry_price": 56.596351,
      "current_price": 56.615,
      "market_value": 13485.093417,
      "cost_basis": 13480.651407,
      "unrealized_pl": 4.44201,
      "unrealized_plpc": 0.0003295100411612,
      "unrealized_intraday_pl": 4.441994,
      "unrealized_intraday_plpc": 0.0003295088538838
    },
    {
      "symbol": "PPLT",
      "qty": 21.664202241,
      "avg_entry_price": 214.08,
      "current_price": 215.07,
      "market_value": 4659.319976,
      "cost_basis": 4637.872416,
      "unrealized_pl": 21.44756,
      "unrealized_plpc": 0.0046244394145059,
      "unrealized_intraday_pl": 21.44756,
      "unrealized_intraday_plpc": 0.0046244394145059
    },
    {
      "symbol": "REMX",
      "qty": 176.642758464,
      "avg_entry_price": 90.371979,
      "current_price": 90.99,
      "market_value": 16072.724593,
      "cost_basis": 15963.555733,
      "unrealized_pl": 109.16886,
      "unrealized_plpc": 0.006838630554866,
      "unrealized_intraday_pl": 109.168935,
      "unrealized_intraday_plpc": 0.0068386352851967
    },
    {
      "symbol": "SILJ",
      "qty": 150.066752373,
      "avg_entry_price": 31.69,
      "current_price": 31.87,
      "market_value": 4782.627398,
      "cost_basis": 4755.615383,
      "unrealized_pl": 27.012015,
      "unrealized_plpc": 0.0056800251543807,
      "unrealized_intraday_pl": 27.012015,
      "unrealized_intraday_plpc": 0.0056800251543807
    },
    {
      "symbol": "SLV",
      "qty": 143.058645265,
      "avg_entry_price": 82.673744,
      "current_price": 82.0501,
      "market_value": 11737.97615,
      "cost_basis": 11827.19375,
      "unrealized_pl": -89.2176,
      "unrealized_plpc": -0.0075434293109471,
      "unrealized_intraday_pl": -89.217666,
      "unrealized_intraday_plpc": -0.0075434348492121
    },
    {
      "symbol": "XLB",
      "qty": 247.074601994,
      "avg_entry_price": 48.7,
      "current_price": 48.73,
      "market_value": 12039.945355,
      "cost_basis": 12032.533117,
      "unrealized_pl": 7.412238,
      "unrealized_plpc": 0.0006160164221387,
      "unrealized_intraday_pl": 7.412238,
      "unrealized_intraday_plpc": 0.0006160164221387
    },
    {
      "symbol": "XME",
      "qty": 108.53906289,
      "avg_entry_price": 120.678107,
      "current_price": 121.73,
      "market_value": 13212.460126,
      "cost_basis": 13098.288665,
      "unrealized_pl": 114.171461,
      "unrealized_plpc": 0.0087165173955189,
      "unrealized_intraday_pl": 114.171481,
      "unrealized_intraday_plpc": 0.0087165189357453
    }
  ],
  "scanner": {
    "timestamp": "2026-01-14T12:41:10.019036",
    "market_regime": "RISK_ON",
    "top_scorers": [
      {
        "ticker": "ASTI",
        "momentum": 100,
        "volatility": 100,
        "relative_strength": 100,
        "breakout": 77.72,
        "volume": 26.25,
        "rsi": 47.44,
        "composite": 89.28,
        "price": 4.7,
        "return_30d": 195.64,
        "is_overbought": 0,
        "is_oversold": 0,
        "has_loss_penalty": 0
      },
      {
        "ticker": "AP",
        "momentum": 100,
        "volatility": 42.04,
        "relative_strength": 100,
        "breakout": 100,
        "volume": 70.76,
        "rsi": 69.15,
        "composite": 88.38,
        "price": 5.98,
        "return_30d": 118.07,
        "is_overbought": 0,
        "is_oversold": 0,
        "has_loss_penalty": 0
      },
      {
        "ticker": "TROO",
        "momentum": 100,
        "volatility": 72.68,
        "relative_strength": 100,
        "breakout": 49.4,
        "volume": 100,
        "rsi": 67.99,
        "composite": 88.31,
        "price": 3.75,
        "return_30d": 186.26,
        "is_overbought": 0,
        "is_oversold": 0,
        "has_loss_penalty": 0
      },
      {
        "ticker": "ISSC",
        "momentum": 100,
        "volatility": 32.39,
        "relative_strength": 100,
        "breakout": 100,
        "volume": 82.54,
        "rsi": 64.56,
        "composite": 88.11,
        "price": 21.37,
        "return_30d": 122.37,
        "is_overbought": 0,
        "is_oversold": 0,
        "has_loss_penalty": 0
      },
      {
        "ticker": "RKLX",
        "momentum": 100,
        "volatility": 61.29,
        "relative_strength": 100,
        "breakout": 100,
        "volume": 30.28,
        "rsi": 55.04,
        "composite": 87.22,
        "price": 61.84,
        "return_30d": 234.73,
        "is_overbought": 0,
        "is_oversold": 0,
        "has_loss_penalty": 0
      },
      {
        "ticker": "YCBD",
        "momentum": 100,
        "volatility": 100,
        "relative_strength": 100,
        "breakout": 0,
        "volume": 0.92,
        "rsi": 19.73,
        "composite": 86.36,
        "price": 1.02,
        "return_30d": 70.66,
        "is_overbought": 0,
        "is_oversold": 1,
        "has_loss_penalty": 0
      },
      {
        "ticker": "ORMP",
        "momentum": 100,
        "volatility": 23.51,
        "relative_strength": 100,
        "breakout": 100,
        "volume": 100,
        "rsi": 72.78,
        "composite": 86.06,
        "price": 3.67,
        "return_30d": 33.45,
        "is_overbought": 1,
        "is_oversold": 0,
        "has_loss_penalty": 0
      },
      {
        "ticker": "TENX",
        "momentum": 100,
        "volatility": 38.5,
        "relative_strength": 100,
        "breakout": 100,
        "volume": 100,
        "rsi": 75.6,
        "composite": 85.69,
        "price": 16.64,
        "return_30d": 84.68,
        "is_overbought": 1,
        "is_oversold": 0,
        "has_loss_penalty": 0
      },
      {
        "ticker": "TE",
        "momentum": 100,
        "volatility": 46.9,
        "relative_strength": 100,
        "breakout": 95.0,
        "volume": 41.75,
        "rsi": 58.77,
        "composite": 85.46,
        "price": 8.0,
        "return_30d": 68.67,
        "is_overbought": 0,
        "is_oversold": 0,
        "has_loss_penalty": 0
      },
      {
        "ticker": "OSS",
        "momentum": 100,
        "volatility": 35.69,
        "relative_strength": 100,
        "breakout": 100,
        "volume": 100,
        "rsi": 75.63,
        "composite": 85.27,
        "price": 11.3,
        "return_30d": 86.16,
        "is_overbought": 1,
        "is_oversold": 0,
        "has_loss_penalty": 0
      }
    ],
    "total_tickers_scored": 5279
  }
}