{
  "last_updated": "2026-01-09T13:00:14.967856",
  "event_count": 200,
  "events": [
    {
      "timestamp": "2026-01-07T16:11:29.515289",
      "type": "portfolio",
      "level": "INFO",
      "source": "Profit Taker",
      "message": "\ud83d\udc40 Monitoring 4 positions: AA +0.1%, HUT -2.1%, RKLB -1.7%, SLV +0.7%",
      "metadata": {
        "portfolio_value": "100K",
        "positions_count": 4,
        "avg_return": -0.8
      }
    },
    {
      "timestamp": "2026-01-07T16:12:29.576800",
      "type": "portfolio",
      "level": "INFO",
      "source": "Profit Taker",
      "message": "\ud83d\udc40 Monitoring 4 positions: AA +0.2%, HUT -2.1%, RKLB -1.5%, SLV +0.6%",
      "metadata": {
        "portfolio_value": "100K",
        "positions_count": 4,
        "avg_return": -0.7
      }
    },
    {
      "timestamp": "2026-01-07T16:13:29.633056",
      "type": "portfolio",
      "level": "INFO",
      "source": "Profit Taker",
      "message": "\ud83d\udc40 Monitoring 4 positions: AA +0.2%, HUT -2.2%, RKLB -1.6%, SLV +0.5%",
      "metadata": {
        "portfolio_value": "100K",
        "positions_count": 4,
        "avg_return": -0.8
      }
    },
    {
      "timestamp": "2026-01-07T16:14:29.701107",
      "type": "portfolio",
      "level": "INFO",
      "source": "Profit Taker",
      "message": "\ud83d\udc40 Monitoring 4 positions: AA +0.2%, HUT -2.2%, RKLB -1.6%, SLV +0.4%",
      "metadata": {
        "portfolio_value": "100K",
        "positions_count": 4,
        "avg_return": -0.8
      }
    },
    {
      "timestamp": "2026-01-07T16:15:29.770397",
      "type": "portfolio",
      "level": "INFO",
      "source": "Profit Taker",
      "message": "\ud83d\udc40 Monitoring 4 positions: AA +0.2%, HUT -2.1%, RKLB -1.6%, SLV +0.4%",
      "metadata": {
        "portfolio_value": "100K",
        "positions_count": 4,
        "avg_return": -0.8
      }
    },
    {
      "timestamp": "2026-01-07T16:16:29.851524",
      "type": "portfolio",
      "level": "INFO",
      "source": "Profit Taker",
      "message": "\ud83d\udc40 Monitoring 4 positions: AA +0.2%, HUT -2.1%, RKLB -2.0%, SLV +0.4%",
      "metadata": {
        "portfolio_value": "100K",
        "positions_count": 4,
        "avg_return": -0.9
      }
    },
    {
      "timestamp": "2026-01-07T16:17:29.904023",
      "type": "portfolio",
      "level": "INFO",
      "source": "Profit Taker",
      "message": "\ud83d\udc40 Monitoring 4 positions: AA +0.3%, HUT -2.3%, RKLB -1.7%, SLV +0.2%",
      "metadata": {
        "portfolio_value": "100K",
        "positions_count": 4,
        "avg_return": -0.9
      }
    },
    {
      "timestamp": "2026-01-07T16:18:29.963656",
      "type": "portfolio",
      "level": "INFO",
      "source": "Profit Taker",
      "message": "\ud83d\udc40 Monitoring 4 positions: AA -0.5%, HUT -2.3%, RKLB -2.2%, SLV +0.4%",
      "metadata": {
        "portfolio_value": "99K",
        "positions_count": 4,
        "avg_return": -1.2
      }
    },
    {
      "timestamp": "2026-01-07T16:19:30.031464",
      "type": "portfolio",
      "level": "INFO",
      "source": "Profit Taker",
      "message": "\ud83d\udc40 Monitoring 4 positions: AA +0.3%, HUT -2.3%, RKLB -2.2%, SLV +0.3%",
      "metadata": {
        "portfolio_value": "100K",
        "positions_count": 4,
        "avg_return": -1.0
      }
    },
    {
      "timestamp": "2026-01-07T16:20:30.092824",
      "type": "portfolio",
      "level": "INFO",
      "source": "Profit Taker",
      "message": "\ud83d\udc40 Monitoring 4 positions: AA +0.4%, HUT -2.3%, RKLB -2.1%, SLV +0.3%",
      "metadata": {
        "portfolio_value": "100K",
        "positions_count": 4,
        "avg_return": -0.9
      }
    },
    {
      "timestamp": "2026-01-07T16:21:30.161338",
      "type": "portfolio",
      "level": "INFO",
      "source": "Profit Taker",
      "message": "\ud83d\udc40 Monitoring 4 positions: AA +0.3%, HUT -2.3%, RKLB -2.0%, SLV +0.2%",
      "metadata": {
        "portfolio_value": "100K",
        "positions_count": 4,
        "avg_return": -1.0
      }
    },
    {
      "timestamp": "2026-01-07T16:22:30.212940",
      "type": "portfolio",
      "level": "INFO",
      "source": "Profit Taker",
      "message": "\ud83d\udc40 Monitoring 4 positions: AA +0.3%, HUT -2.3%, RKLB -2.1%, SLV +0.3%",
      "metadata": {
        "portfolio_value": "100K",
        "positions_count": 4,
        "avg_return": -1.0
      }
    },
    {
      "timestamp": "2026-01-07T16:23:30.371667",
      "type": "portfolio",
      "level": "INFO",
      "source": "Profit Taker",
      "message": "\ud83d\udc40 Monitoring 4 positions: AA +0.3%, HUT -2.3%, RKLB -2.1%, SLV +0.2%",
      "metadata": {
        "portfolio_value": "100K",
        "positions_count": 4,
        "avg_return": -1.0
      }
    },
    {
      "timestamp": "2026-01-07T16:24:30.423741",
      "type": "portfolio",
      "level": "INFO",
      "source": "Profit Taker",
      "message": "\ud83d\udc40 Monitoring 4 positions: AA +0.3%, HUT -2.3%, RKLB -2.3%, SLV +0.2%",
      "metadata": {
        "portfolio_value": "100K",
        "positions_count": 4,
        "avg_return": -1.0
      }
    },
    {
      "timestamp": "2026-01-07T16:25:30.483938",
      "type": "portfolio",
      "level": "INFO",
      "source": "Profit Taker",
      "message": "\ud83d\udc40 Monitoring 4 positions: AA +0.3%, HUT -2.3%, RKLB -1.8%, SLV +0.2%",
      "metadata": {
        "portfolio_value": "100K",
        "positions_count": 4,
        "avg_return": -0.9
      }
    },
    {
      "timestamp": "2026-01-07T16:26:30.535833",
      "type": "portfolio",
      "level": "INFO",
      "source": "Profit Taker",
      "message": "\ud83d\udc40 Monitoring 4 positions: AA +0.3%, HUT -2.3%, RKLB -2.3%, SLV +0.2%",
      "metadata": {
        "portfolio_value": "100K",
        "positions_count": 4,
        "avg_return": -1.0
      }
    },
    {
      "timestamp": "2026-01-07T16:27:30.581502",
      "type": "portfolio",
      "level": "INFO",
      "source": "Profit Taker",
      "message": "\ud83d\udc40 Monitoring 4 positions: AA +0.3%, HUT -2.4%, RKLB -2.3%, SLV +0.2%",
      "metadata": {
        "portfolio_value": "100K",
        "positions_count": 4,
        "avg_return": -1.0
      }
    },
    {
      "timestamp": "2026-01-07T16:28:30.629279",
      "type": "portfolio",
      "level": "INFO",
      "source": "Profit Taker",
      "message": "\ud83d\udc40 Monitoring 4 positions: AA +0.3%, HUT -2.4%, RKLB -2.2%, SLV +0.3%",
      "metadata": {
        "portfolio_value": "100K",
        "positions_count": 4,
        "avg_return": -1.0
      }
    },
    {
      "timestamp": "2026-01-07T16:29:30.688467",
      "type": "portfolio",
      "level": "INFO",
      "source": "Profit Taker",
      "message": "\ud83d\udc40 Monitoring 4 positions: AA +0.3%, HUT -2.4%, RKLB -2.1%, SLV +0.3%",
      "metadata": {
        "portfolio_value": "100K",
        "positions_count": 4,
        "avg_return": -1.0
      }
    },
    {
      "timestamp": "2026-01-07T16:30:30.774607",
      "type": "portfolio",
      "level": "INFO",
      "source": "Profit Taker",
      "message": "\ud83d\udc40 Monitoring 4 positions: AA +0.2%, HUT -2.4%, RKLB -2.3%, SLV +0.4%",
      "metadata": {
        "portfolio_value": "100K",
        "positions_count": 4,
        "avg_return": -1.0
      }
    },
    {
      "timestamp": "2026-01-07T16:31:30.829564",
      "type": "portfolio",
      "level": "INFO",
      "source": "Profit Taker",
      "message": "\ud83d\udc40 Monitoring 4 positions: AA +0.3%, HUT -2.3%, RKLB -2.1%, SLV +0.3%",
      "metadata": {
        "portfolio_value": "100K",
        "positions_count": 4,
        "avg_return": -1.0
      }
    },
    {
      "timestamp": "2026-01-07T16:32:30.887520",
      "type": "portfolio",
      "level": "INFO",
      "source": "Profit Taker",
      "message": "\ud83d\udc40 Monitoring 4 positions: AA +0.3%, HUT -2.4%, RKLB -2.1%, SLV +0.2%",
      "metadata": {
        "portfolio_value": "100K",
        "positions_count": 4,
        "avg_return": -1.0
      }
    },
    {
      "timestamp": "2026-01-07T16:33:30.940254",
      "type": "portfolio",
      "level": "INFO",
      "source": "Profit Taker",
      "message": "\ud83d\udc40 Monitoring 4 positions: AA +0.2%, HUT -2.1%, RKLB -2.1%, SLV +0.2%",
      "metadata": {
        "portfolio_value": "100K",
        "positions_count": 4,
        "avg_return": -0.9
      }
    },
    {
      "timestamp": "2026-01-07T16:34:30.993557",
      "type": "portfolio",
      "level": "INFO",
      "source": "Profit Taker",
      "message": "\ud83d\udc40 Monitoring 4 positions: AA +0.2%, HUT -2.1%, RKLB -2.1%, SLV +0.3%",
      "metadata": {
        "portfolio_value": "100K",
        "positions_count": 4,
        "avg_return": -0.9
      }
    },
    {
      "timestamp": "2026-01-07T16:35:31.054866",
      "type": "portfolio",
      "level": "INFO",
      "source": "Profit Taker",
      "message": "\ud83d\udc40 Monitoring 4 positions: AA +0.2%, HUT -2.1%, RKLB -0.5%, SLV +0.3%",
      "metadata": {
        "portfolio_value": "100K",
        "positions_count": 4,
        "avg_return": -0.5
      }
    },
    {
      "timestamp": "2026-01-07T16:36:31.105723",
      "type": "portfolio",
      "level": "INFO",
      "source": "Profit Taker",
      "message": "\ud83d\udc40 Monitoring 4 positions: AA +0.2%, HUT -2.1%, RKLB -2.2%, SLV +0.3%",
      "metadata": {
        "portfolio_value": "100K",
        "positions_count": 4,
        "avg_return": -0.9
      }
    },
    {
      "timestamp": "2026-01-07T16:37:31.183189",
      "type": "portfolio",
      "level": "INFO",
      "source": "Profit Taker",
      "message": "\ud83d\udc40 Monitoring 4 positions: AA +0.2%, HUT -2.1%, RKLB -2.1%, SLV +0.3%",
      "metadata": {
        "portfolio_value": "100K",
        "positions_count": 4,
        "avg_return": -0.9
      }
    },
    {
      "timestamp": "2026-01-07T16:38:31.233310",
      "type": "portfolio",
      "level": "INFO",
      "source": "Profit Taker",
      "message": "\ud83d\udc40 Monitoring 4 positions: AA +0.2%, HUT -2.1%, RKLB -2.0%, SLV +0.3%",
      "metadata": {
        "portfolio_value": "100K",
        "positions_count": 4,
        "avg_return": -0.9
      }
    },
    {
      "timestamp": "2026-01-07T16:39:31.293896",
      "type": "portfolio",
      "level": "INFO",
      "source": "Profit Taker",
      "message": "\ud83d\udc40 Monitoring 4 positions: AA +0.2%, HUT -2.1%, RKLB -1.8%, SLV +0.3%",
      "metadata": {
        "portfolio_value": "100K",
        "positions_count": 4,
        "avg_return": -0.8
      }
    },
    {
      "timestamp": "2026-01-07T16:40:31.350766",
      "type": "portfolio",
      "level": "INFO",
      "source": "Profit Taker",
      "message": "\ud83d\udc40 Monitoring 4 positions: AA +0.2%, HUT -2.1%, RKLB -1.7%, SLV +0.3%",
      "metadata": {
        "portfolio_value": "100K",
        "positions_count": 4,
        "avg_return": -0.8
      }
    },
    {
      "timestamp": "2026-01-07T16:41:31.404625",
      "type": "portfolio",
      "level": "INFO",
      "source": "Profit Taker",
      "message": "\ud83d\udc40 Monitoring 4 positions: AA +0.2%, HUT -2.1%, RKLB -1.5%, SLV +0.2%",
      "metadata": {
        "portfolio_value": "100K",
        "positions_count": 4,
        "avg_return": -0.8
      }
    },
    {
      "timestamp": "2026-01-07T16:42:31.459205",
      "type": "portfolio",
      "level": "INFO",
      "source": "Profit Taker",
      "message": "\ud83d\udc40 Monitoring 4 positions: AA +0.2%, HUT -2.4%, RKLB -0.8%, SLV +0.2%",
      "metadata": {
        "portfolio_value": "100K",
        "positions_count": 4,
        "avg_return": -0.7
      }
    },
    {
      "timestamp": "2026-01-07T16:43:31.503117",
      "type": "portfolio",
      "level": "INFO",
      "source": "Profit Taker",
      "message": "\ud83d\udc40 Monitoring 4 positions: AA +0.2%, HUT -2.1%, RKLB -0.8%, SLV +0.2%",
      "metadata": {
        "portfolio_value": "100K",
        "positions_count": 4,
        "avg_return": -0.6
      }
    },
    {
      "timestamp": "2026-01-07T16:44:31.655867",
      "type": "portfolio",
      "level": "INFO",
      "source": "Profit Taker",
      "message": "\ud83d\udc40 Monitoring 4 positions: AA +0.2%, HUT -2.1%, RKLB -0.3%, SLV +0.2%",
      "metadata": {
        "portfolio_value": "100K",
        "positions_count": 4,
        "avg_return": -0.5
      }
    },
    {
      "timestamp": "2026-01-07T16:45:31.711159",
      "type": "portfolio",
      "level": "INFO",
      "source": "Profit Taker",
      "message": "\ud83d\udc40 Monitoring 4 positions: AA +0.2%, HUT -2.1%, RKLB -0.1%, SLV +0.2%",
      "metadata": {
        "portfolio_value": "100K",
        "positions_count": 4,
        "avg_return": -0.4
      }
    },
    {
      "timestamp": "2026-01-07T16:46:31.775973",
      "type": "portfolio",
      "level": "INFO",
      "source": "Profit Taker",
      "message": "\ud83d\udc40 Monitoring 4 positions: AA +0.2%, HUT -2.1%, RKLB -0.5%, SLV +0.2%",
      "metadata": {
        "portfolio_value": "100K",
        "positions_count": 4,
        "avg_return": -0.5
      }
    },
    {
      "timestamp": "2026-01-07T16:47:31.832773",
      "type": "portfolio",
      "level": "INFO",
      "source": "Profit Taker",
      "message": "\ud83d\udc40 Monitoring 4 positions: AA +0.2%, HUT -2.1%, RKLB -0.6%, SLV +0.3%",
      "metadata": {
        "portfolio_value": "100K",
        "positions_count": 4,
        "avg_return": -0.5
      }
    },
    {
      "timestamp": "2026-01-07T16:48:31.891225",
      "type": "portfolio",
      "level": "INFO",
      "source": "Profit Taker",
      "message": "\ud83d\udc40 Monitoring 4 positions: AA +0.2%, HUT -2.1%, RKLB -0.9%, SLV +0.3%",
      "metadata": {
        "portfolio_value": "100K",
        "positions_count": 4,
        "avg_return": -0.6
      }
    },
    {
      "timestamp": "2026-01-07T16:49:31.941737",
      "type": "portfolio",
      "level": "INFO",
      "source": "Profit Taker",
      "message": "\ud83d\udc40 Monitoring 4 positions: AA +0.2%, HUT -2.1%, RKLB -0.5%, SLV +0.3%",
      "metadata": {
        "portfolio_value": "100K",
        "positions_count": 4,
        "avg_return": -0.5
      }
    },
    {
      "timestamp": "2026-01-07T16:50:31.988601",
      "type": "portfolio",
      "level": "INFO",
      "source": "Profit Taker",
      "message": "\ud83d\udc40 Monitoring 4 positions: AA +0.2%, HUT -2.1%, RKLB -0.4%, SLV +0.3%",
      "metadata": {
        "portfolio_value": "100K",
        "positions_count": 4,
        "avg_return": -0.5
      }
    },
    {
      "timestamp": "2026-01-07T16:51:32.076409",
      "type": "portfolio",
      "level": "INFO",
      "source": "Profit Taker",
      "message": "\ud83d\udc40 Monitoring 4 positions: AA +0.3%, HUT -1.7%, RKLB +0.0%, SLV +0.2%",
      "metadata": {
        "portfolio_value": "100K",
        "positions_count": 4,
        "avg_return": -0.3
      }
    },
    {
      "timestamp": "2026-01-07T16:52:32.132921",
      "type": "portfolio",
      "level": "INFO",
      "source": "Profit Taker",
      "message": "\ud83d\udc40 Monitoring 4 positions: AA +0.2%, HUT -1.7%, RKLB -0.1%, SLV +0.3%",
      "metadata": {
        "portfolio_value": "100K",
        "positions_count": 4,
        "avg_return": -0.3
      }
    },
    {
      "timestamp": "2026-01-07T16:53:32.188622",
      "type": "portfolio",
      "level": "INFO",
      "source": "Profit Taker",
      "message": "\ud83d\udc40 Monitoring 4 positions: AA +0.2%, HUT -1.7%, RKLB -0.1%, SLV +0.3%",
      "metadata": {
        "portfolio_value": "100K",
        "positions_count": 4,
        "avg_return": -0.3
      }
    },
    {
      "timestamp": "2026-01-07T16:54:32.247287",
      "type": "portfolio",
      "level": "INFO",
      "source": "Profit Taker",
      "message": "\ud83d\udc40 Monitoring 4 positions: AA +0.2%, HUT -1.7%, RKLB -0.4%, SLV +0.3%",
      "metadata": {
        "portfolio_value": "100K",
        "positions_count": 4,
        "avg_return": -0.4
      }
    },
    {
      "timestamp": "2026-01-07T16:55:32.303900",
      "type": "portfolio",
      "level": "INFO",
      "source": "Profit Taker",
      "message": "\ud83d\udc40 Monitoring 4 positions: AA +0.2%, HUT -1.7%, RKLB -0.4%, SLV +0.3%",
      "metadata": {
        "portfolio_value": "100K",
        "positions_count": 4,
        "avg_return": -0.4
      }
    },
    {
      "timestamp": "2026-01-07T16:56:32.355000",
      "type": "portfolio",
      "level": "INFO",
      "source": "Profit Taker",
      "message": "\ud83d\udc40 Monitoring 4 positions: AA +0.2%, HUT -1.7%, RKLB -0.2%, SLV +0.3%",
      "metadata": {
        "portfolio_value": "100K",
        "positions_count": 4,
        "avg_return": -0.4
      }
    },
    {
      "timestamp": "2026-01-07T16:57:32.430004",
      "type": "portfolio",
      "level": "INFO",
      "source": "Profit Taker",
      "message": "\ud83d\udc40 Monitoring 4 positions: AA +0.2%, HUT -1.7%, RKLB -0.3%, SLV +0.3%",
      "metadata": {
        "portfolio_value": "100K",
        "positions_count": 4,
        "avg_return": -0.4
      }
    },
    {
      "timestamp": "2026-01-07T16:58:32.511645",
      "type": "portfolio",
      "level": "INFO",
      "source": "Profit Taker",
      "message": "\ud83d\udc40 Monitoring 4 positions: AA +0.2%, HUT -1.7%, RKLB -0.1%, SLV +0.3%",
      "metadata": {
        "portfolio_value": "100K",
        "positions_count": 4,
        "avg_return": -0.3
      }
    },
    {
      "timestamp": "2026-01-07T16:59:32.574505",
      "type": "portfolio",
      "level": "INFO",
      "source": "Profit Taker",
      "message": "\ud83d\udc40 Monitoring 4 positions: AA +0.2%, HUT -1.7%, RKLB -0.3%, SLV +0.2%",
      "metadata": {
        "portfolio_value": "100K",
        "positions_count": 4,
        "avg_return": -0.4
      }
    },
    {
      "timestamp": "2026-01-07T17:00:32.641911",
      "type": "portfolio",
      "level": "INFO",
      "source": "Profit Taker",
      "message": "\ud83d\udc40 Monitoring 4 positions: AA +0.2%, HUT -1.7%, RKLB -0.2%, SLV +0.1%",
      "metadata": {
        "portfolio_value": "100K",
        "positions_count": 4,
        "avg_return": -0.4
      }
    },
    {
      "timestamp": "2026-01-07T17:01:32.705594",
      "type": "portfolio",
      "level": "INFO",
      "source": "Profit Taker",
      "message": "\ud83d\udc40 Monitoring 4 positions: AA +0.3%, HUT -1.9%, RKLB -0.4%, SLV +0.2%",
      "metadata": {
        "portfolio_value": "100K",
        "positions_count": 4,
        "avg_return": -0.4
      }
    },
    {
      "timestamp": "2026-01-07T17:02:32.777372",
      "type": "portfolio",
      "level": "INFO",
      "source": "Profit Taker",
      "message": "\ud83d\udc40 Monitoring 4 positions: AA +0.3%, HUT -2.1%, RKLB -0.4%, SLV +0.2%",
      "metadata": {
        "portfolio_value": "100K",
        "positions_count": 4,
        "avg_return": -0.5
      }
    },
    {
      "timestamp": "2026-01-07T17:03:32.838676",
      "type": "portfolio",
      "level": "INFO",
      "source": "Profit Taker",
      "message": "\ud83d\udc40 Monitoring 4 positions: AA +0.3%, HUT -2.4%, RKLB -0.6%, SLV +0.2%",
      "metadata": {
        "portfolio_value": "100K",
        "positions_count": 4,
        "avg_return": -0.6
      }
    },
    {
      "timestamp": "2026-01-07T17:04:32.880516",
      "type": "portfolio",
      "level": "INFO",
      "source": "Profit Taker",
      "message": "\ud83d\udc40 Monitoring 4 positions: AA +0.3%, HUT -2.4%, RKLB -0.7%, SLV +0.2%",
      "metadata": {
        "portfolio_value": "100K",
        "positions_count": 4,
        "avg_return": -0.6
      }
    },
    {
      "timestamp": "2026-01-07T17:05:32.957572",
      "type": "portfolio",
      "level": "INFO",
      "source": "Profit Taker",
      "message": "\ud83d\udc40 Monitoring 4 positions: AA +0.3%, HUT -1.7%, RKLB -0.6%, SLV +0.2%",
      "metadata": {
        "portfolio_value": "100K",
        "positions_count": 4,
        "avg_return": -0.4
      }
    },
    {
      "timestamp": "2026-01-07T17:06:33.014857",
      "type": "portfolio",
      "level": "INFO",
      "source": "Profit Taker",
      "message": "\ud83d\udc40 Monitoring 4 positions: AA +0.3%, HUT -1.7%, RKLB -1.7%, SLV +0.3%",
      "metadata": {
        "portfolio_value": "100K",
        "positions_count": 4,
        "avg_return": -0.7
      }
    },
    {
      "timestamp": "2026-01-07T17:07:33.075063",
      "type": "portfolio",
      "level": "INFO",
      "source": "Profit Taker",
      "message": "\ud83d\udc40 Monitoring 4 positions: AA +0.4%, HUT -2.0%, RKLB -0.7%, SLV +0.3%",
      "metadata": {
        "portfolio_value": "100K",
        "positions_count": 4,
        "avg_return": -0.5
      }
    },
    {
      "timestamp": "2026-01-07T17:08:33.129919",
      "type": "portfolio",
      "level": "INFO",
      "source": "Profit Taker",
      "message": "\ud83d\udc40 Monitoring 4 positions: AA +0.4%, HUT -2.0%, RKLB -0.7%, SLV +0.3%",
      "metadata": {
        "portfolio_value": "100K",
        "positions_count": 4,
        "avg_return": -0.5
      }
    },
    {
      "timestamp": "2026-01-07T17:09:33.185174",
      "type": "portfolio",
      "level": "INFO",
      "source": "Profit Taker",
      "message": "\ud83d\udc40 Monitoring 4 positions: AA +0.4%, HUT -2.0%, RKLB -1.7%, SLV +0.2%",
      "metadata": {
        "portfolio_value": "100K",
        "positions_count": 4,
        "avg_return": -0.8
      }
    },
    {
      "timestamp": "2026-01-07T17:10:33.240071",
      "type": "portfolio",
      "level": "INFO",
      "source": "Profit Taker",
      "message": "\ud83d\udc40 Monitoring 4 positions: AA +0.4%, HUT -2.0%, RKLB -1.0%, SLV +0.3%",
      "metadata": {
        "portfolio_value": "100K",
        "positions_count": 4,
        "avg_return": -0.6
      }
    },
    {
      "timestamp": "2026-01-07T17:33:11.631156",
      "type": "portfolio",
      "level": "INFO",
      "source": "Profit Taker",
      "message": "\ud83d\udc40 Monitoring 4 positions: AA +0.4%, HUT -2.0%, RKLB -1.1%, SLV +0.3%",
      "metadata": {
        "portfolio_value": "100K",
        "positions_count": 4,
        "avg_return": -0.6
      }
    },
    {
      "timestamp": "2026-01-07T19:15:00.473991",
      "type": "portfolio",
      "level": "INFO",
      "source": "Profit Taker",
      "message": "\ud83d\udc40 Monitoring 4 positions: AA +0.4%, HUT -2.0%, RKLB -1.1%, SLV +0.3%",
      "metadata": {
        "portfolio_value": "100K",
        "positions_count": 4,
        "avg_return": -0.6
      }
    },
    {
      "timestamp": "2026-01-07T20:20:37.716236",
      "type": "portfolio",
      "level": "INFO",
      "source": "Profit Taker",
      "message": "\ud83d\udc40 Monitoring 4 positions: AA +0.2%, HUT -1.7%, RKLB -2.3%, SLV +0.7%",
      "metadata": {
        "portfolio_value": "100K",
        "positions_count": 4,
        "avg_return": -0.8
      }
    },
    {
      "timestamp": "2026-01-07T20:56:46.267864",
      "type": "portfolio",
      "level": "INFO",
      "source": "Profit Taker",
      "message": "\ud83d\udc40 Monitoring 4 positions: AA -0.7%, HUT -2.0%, RKLB -1.8%, SLV +0.4%",
      "metadata": {
        "portfolio_value": "99K",
        "positions_count": 4,
        "avg_return": -1.0
      }
    },
    {
      "timestamp": "2026-01-07T22:19:27.243839",
      "type": "portfolio",
      "level": "INFO",
      "source": "Profit Taker",
      "message": "\ud83d\udc40 Monitoring 4 positions: AA -0.7%, HUT -2.0%, RKLB -1.8%, SLV +0.4%",
      "metadata": {
        "portfolio_value": "99K",
        "positions_count": 4,
        "avg_return": -1.0
      }
    },
    {
      "timestamp": "2026-01-08T00:14:28.128549",
      "type": "portfolio",
      "level": "INFO",
      "source": "Profit Taker",
      "message": "\ud83d\udc40 Monitoring 4 positions: AA +0.2%, HUT -2.1%, RKLB -1.6%, SLV +0.4%",
      "metadata": {
        "portfolio_value": "100K",
        "positions_count": 4,
        "avg_return": -0.8
      }
    },
    {
      "timestamp": "2026-01-08T02:07:30.138378",
      "type": "portfolio",
      "level": "INFO",
      "source": "Profit Taker",
      "message": "\ud83d\udc40 Monitoring 4 positions: AA +0.2%, HUT -2.1%, RKLB -1.6%, SLV +0.4%",
      "metadata": {
        "portfolio_value": "100K",
        "positions_count": 4,
        "avg_return": -0.8
      }
    },
    {
      "timestamp": "2026-01-08T04:28:02.072748",
      "type": "portfolio",
      "level": "INFO",
      "source": "Profit Taker",
      "message": "\ud83d\udc40 Monitoring 4 positions: AA +0.2%, HUT -2.1%, RKLB -1.6%, SLV +0.4%",
      "metadata": {
        "portfolio_value": "100K",
        "positions_count": 4,
        "avg_return": -0.8
      }
    },
    {
      "timestamp": "2026-01-08T06:38:28.095978",
      "type": "portfolio",
      "level": "INFO",
      "source": "Profit Taker",
      "message": "\ud83d\udc40 Monitoring 4 positions: AA -3.6%, HUT -3.1%, RKLB -2.1%, SLV -2.7%",
      "metadata": {
        "portfolio_value": "97K",
        "positions_count": 4,
        "avg_return": -2.9
      }
    },
    {
      "timestamp": "2026-01-08T06:39:28.276567",
      "type": "portfolio",
      "level": "INFO",
      "source": "Profit Taker",
      "message": "\ud83d\udc40 Monitoring 4 positions: AA -3.2%, HUT -2.5%, RKLB -1.9%, SLV -2.9%",
      "metadata": {
        "portfolio_value": "97K",
        "positions_count": 4,
        "avg_return": -2.6
      }
    },
    {
      "timestamp": "2026-01-08T06:40:28.333282",
      "type": "portfolio",
      "level": "INFO",
      "source": "Profit Taker",
      "message": "\ud83d\udc40 Monitoring 4 positions: AA -3.2%, HUT -2.5%, RKLB -1.9%, SLV -2.9%",
      "metadata": {
        "portfolio_value": "97K",
        "positions_count": 4,
        "avg_return": -2.6
      }
    },
    {
      "timestamp": "2026-01-08T06:41:28.386354",
      "type": "portfolio",
      "level": "INFO",
      "source": "Profit Taker",
      "message": "\ud83d\udc40 Monitoring 4 positions: AA -3.2%, HUT -2.5%, RKLB -2.0%, SLV -2.8%",
      "metadata": {
        "portfolio_value": "97K",
        "positions_count": 4,
        "avg_return": -2.6
      }
    },
    {
      "timestamp": "2026-01-08T06:42:28.448494",
      "type": "portfolio",
      "level": "INFO",
      "source": "Profit Taker",
      "message": "\ud83d\udc40 Monitoring 4 positions: AA -3.2%, HUT -2.5%, RKLB -1.8%, SLV -2.9%",
      "metadata": {
        "portfolio_value": "97K",
        "positions_count": 4,
        "avg_return": -2.6
      }
    },
    {
      "timestamp": "2026-01-08T06:43:28.506127",
      "type": "portfolio",
      "level": "INFO",
      "source": "Profit Taker",
      "message": "\ud83d\udc40 Monitoring 4 positions: AA -3.2%, HUT -2.5%, RKLB -1.7%, SLV -2.9%",
      "metadata": {
        "portfolio_value": "97K",
        "positions_count": 4,
        "avg_return": -2.6
      }
    },
    {
      "timestamp": "2026-01-08T06:44:28.557963",
      "type": "portfolio",
      "level": "INFO",
      "source": "Profit Taker",
      "message": "\ud83d\udc40 Monitoring 4 positions: AA -3.2%, HUT -2.5%, RKLB -1.7%, SLV -2.9%",
      "metadata": {
        "portfolio_value": "97K",
        "positions_count": 4,
        "avg_return": -2.6
      }
    },
    {
      "timestamp": "2026-01-08T06:45:28.609328",
      "type": "portfolio",
      "level": "INFO",
      "source": "Profit Taker",
      "message": "\ud83d\udc40 Monitoring 4 positions: AA -3.2%, HUT -2.5%, RKLB -1.7%, SLV -2.9%",
      "metadata": {
        "portfolio_value": "97K",
        "positions_count": 4,
        "avg_return": -2.6
      }
    },
    {
      "timestamp": "2026-01-08T06:46:28.656403",
      "type": "portfolio",
      "level": "INFO",
      "source": "Profit Taker",
      "message": "\ud83d\udc40 Monitoring 4 positions: AA -3.4%, HUT -2.5%, RKLB -1.7%, SLV -2.9%",
      "metadata": {
        "portfolio_value": "97K",
        "positions_count": 4,
        "avg_return": -2.6
      }
    },
    {
      "timestamp": "2026-01-08T06:47:28.705157",
      "type": "portfolio",
      "level": "INFO",
      "source": "Profit Taker",
      "message": "\ud83d\udc40 Monitoring 4 positions: AA -3.4%, HUT -2.5%, RKLB -1.8%, SLV -3.0%",
      "metadata": {
        "portfolio_value": "97K",
        "positions_count": 4,
        "avg_return": -2.7
      }
    },
    {
      "timestamp": "2026-01-08T06:48:28.763441",
      "type": "portfolio",
      "level": "INFO",
      "source": "Profit Taker",
      "message": "\ud83d\udc40 Monitoring 4 positions: AA -3.4%, HUT -2.5%, RKLB -1.8%, SLV -3.2%",
      "metadata": {
        "portfolio_value": "97K",
        "positions_count": 4,
        "avg_return": -2.7
      }
    },
    {
      "type": "event",
      "source": "Profit Taker",
      "event_type": "portfolio",
      "level": "INFO",
      "message": "\ud83d\udc40 Monitoring 1 positions: QQQ +0.2%",
      "timestamp": "2026-01-08T16:00:07.987305",
      "portfolio_value": "2K",
      "positions_count": 1,
      "avg_return": 0.2
    },
    {
      "type": "event",
      "source": "Market Scanner",
      "event_type": "scan",
      "level": "INFO",
      "message": "\ud83d\udd0d Daily Market Scan Started",
      "timestamp": "2026-01-09T08:12:38.518642",
      "phase": "start"
    },
    {
      "type": "event",
      "source": "Market Scanner",
      "event_type": "scan",
      "level": "INFO",
      "message": "\ud83d\udd0d Daily market scan initiated - analyzing 5405 tickers",
      "timestamp": "2026-01-09T08:12:38.518724"
    },
    {
      "type": "event",
      "source": "Market Scanner",
      "event_type": "scan",
      "level": "INFO",
      "message": "\ud83d\udcca Loading universe data (5405 tickers)",
      "timestamp": "2026-01-09T08:12:38.518869",
      "phase": "loading"
    },
    {
      "type": "event",
      "source": "Market Scanner",
      "event_type": "scan",
      "level": "INFO",
      "message": "\u2713 Data loaded for 5269/5405 tickers",
      "timestamp": "2026-01-09T08:19:24.650975"
    },
    {
      "type": "event",
      "source": "Market Scanner",
      "event_type": "scan",
      "level": "INFO",
      "message": "\ud83c\udfaf Scoring complete - Top 5: CAMP (95), SMX (95), DRUG (91), OLPX (90), RKLX (90)",
      "timestamp": "2026-01-09T08:19:33.151931"
    },
    {
      "type": "event",
      "source": "Market Scanner",
      "event_type": "scan",
      "level": "INFO",
      "message": "\ud83d\udfe1 Market Regime: UNKNOWN | Hot Sectors: Materials, Financials, Industrials",
      "timestamp": "2026-01-09T08:19:33.153027"
    },
    {
      "type": "event",
      "source": "Market Scanner",
      "event_type": "scan",
      "level": "INFO",
      "message": "\ud83d\udd04 12 rotation opportunities identified - avg score improvement: 42.4 points",
      "timestamp": "2026-01-09T08:19:33.866523"
    },
    {
      "type": "event",
      "source": "Market Scanner",
      "event_type": "scan",
      "level": "INFO",
      "message": "\ud83d\udd0d Daily Market Scan Started",
      "timestamp": "2026-01-09T08:52:40.575944",
      "phase": "start"
    },
    {
      "type": "event",
      "source": "Market Scanner",
      "event_type": "scan",
      "level": "INFO",
      "message": "\ud83d\udd0d Daily market scan initiated - analyzing 5405 tickers",
      "timestamp": "2026-01-09T08:52:40.576021"
    },
    {
      "type": "event",
      "source": "Market Scanner",
      "event_type": "scan",
      "level": "INFO",
      "message": "\ud83d\udcca Loading universe data (5405 tickers)",
      "timestamp": "2026-01-09T08:52:40.576195",
      "phase": "loading"
    },
    {
      "type": "event",
      "source": "Market Scanner",
      "event_type": "scan",
      "level": "INFO",
      "message": "\u2713 Data loaded for 5269/5405 tickers",
      "timestamp": "2026-01-09T08:59:11.744164"
    },
    {
      "type": "event",
      "source": "Market Scanner",
      "event_type": "scan",
      "level": "INFO",
      "message": "\ud83c\udfaf Scoring complete - Top 5: CAMP (95), SMX (95), DRUG (91), OLPX (90), RKLX (90)",
      "timestamp": "2026-01-09T08:59:20.131535"
    },
    {
      "type": "event",
      "source": "Market Scanner",
      "event_type": "scan",
      "level": "INFO",
      "message": "\ud83d\udfe1 Market Regime: UNKNOWN | Hot Sectors: Materials, Financials, Industrials",
      "timestamp": "2026-01-09T08:59:20.132664"
    },
    {
      "type": "event",
      "source": "Market Scanner",
      "event_type": "scan",
      "level": "INFO",
      "message": "\ud83d\udd04 12 rotation opportunities identified - avg score improvement: 42.4 points",
      "timestamp": "2026-01-09T08:59:20.848175"
    },
    {
      "type": "event",
      "source": "Market Scanner",
      "event_type": "scan",
      "level": "INFO",
      "message": "\ud83d\udd0d Daily Market Scan Started",
      "timestamp": "2026-01-09T09:05:24.302935",
      "phase": "start"
    },
    {
      "type": "event",
      "source": "Market Scanner",
      "event_type": "scan",
      "level": "INFO",
      "message": "\ud83d\udd0d Daily market scan initiated - analyzing 5405 tickers",
      "timestamp": "2026-01-09T09:05:24.303034"
    },
    {
      "type": "event",
      "source": "Market Scanner",
      "event_type": "scan",
      "level": "INFO",
      "message": "\ud83d\udcca Loading universe data (5405 tickers)",
      "timestamp": "2026-01-09T09:05:24.303138",
      "phase": "loading"
    },
    {
      "type": "event",
      "source": "Market Scanner",
      "event_type": "scan",
      "level": "INFO",
      "message": "\u2713 Data loaded for 5268/5405 tickers",
      "timestamp": "2026-01-09T09:12:17.379004"
    },
    {
      "type": "event",
      "source": "Market Scanner",
      "event_type": "scan",
      "level": "INFO",
      "message": "\ud83c\udfaf Scoring complete - Top 5: CAMP (95), SMX (95), DRUG (91), OLPX (90), RKLX (90)",
      "timestamp": "2026-01-09T09:12:26.162469"
    },
    {
      "type": "event",
      "source": "Market Scanner",
      "event_type": "scan",
      "level": "INFO",
      "message": "\ud83d\udfe1 Market Regime: UNKNOWN | Hot Sectors: Materials, Financials, Industrials",
      "timestamp": "2026-01-09T09:12:26.163222"
    },
    {
      "type": "event",
      "source": "Market Scanner",
      "event_type": "scan",
      "level": "INFO",
      "message": "\ud83d\udd04 12 rotation opportunities identified - avg score improvement: 42.4 points",
      "timestamp": "2026-01-09T09:12:26.916571"
    },
    {
      "type": "event",
      "source": "Market Scanner",
      "event_type": "scan",
      "level": "INFO",
      "message": "\ud83d\udd0d Daily Market Scan Started",
      "timestamp": "2026-01-09T09:15:45.619246",
      "phase": "start"
    },
    {
      "type": "event",
      "source": "Market Scanner",
      "event_type": "scan",
      "level": "INFO",
      "message": "\ud83d\udd0d Daily market scan initiated - analyzing 5405 tickers",
      "timestamp": "2026-01-09T09:15:45.619340"
    },
    {
      "type": "event",
      "source": "Market Scanner",
      "event_type": "scan",
      "level": "INFO",
      "message": "\ud83d\udcca Loading universe data (5405 tickers)",
      "timestamp": "2026-01-09T09:15:45.619500",
      "phase": "loading"
    },
    {
      "type": "event",
      "source": "Market Scanner",
      "event_type": "scan",
      "level": "INFO",
      "message": "\u2713 Data loaded for 5269/5405 tickers",
      "timestamp": "2026-01-09T09:22:21.906404"
    },
    {
      "type": "event",
      "source": "Market Scanner",
      "event_type": "scan",
      "level": "INFO",
      "message": "\ud83c\udfaf Scoring complete - Top 5: CAMP (95), SMX (95), DRUG (91), OLPX (90), RKLX (90)",
      "timestamp": "2026-01-09T09:22:30.784376"
    },
    {
      "type": "event",
      "source": "Market Scanner",
      "event_type": "scan",
      "level": "INFO",
      "message": "\ud83d\udfe1 Market Regime: UNKNOWN | Hot Sectors: Materials, Financials, Industrials",
      "timestamp": "2026-01-09T09:22:30.785198"
    },
    {
      "type": "event",
      "source": "Market Scanner",
      "event_type": "scan",
      "level": "INFO",
      "message": "\ud83d\udd04 12 rotation opportunities identified - avg score improvement: 42.4 points",
      "timestamp": "2026-01-09T09:22:31.494215"
    },
    {
      "type": "event",
      "source": "Market Scanner",
      "event_type": "scan",
      "level": "INFO",
      "message": "\ud83d\udd0d Daily Market Scan Started",
      "timestamp": "2026-01-09T09:41:51.477797",
      "phase": "start"
    },
    {
      "type": "event",
      "source": "Market Scanner",
      "event_type": "scan",
      "level": "INFO",
      "message": "\ud83d\udd0d Daily market scan initiated - analyzing 5405 tickers",
      "timestamp": "2026-01-09T09:41:51.477857"
    },
    {
      "type": "event",
      "source": "Market Scanner",
      "event_type": "scan",
      "level": "INFO",
      "message": "\ud83d\udcca Loading universe data (5405 tickers)",
      "timestamp": "2026-01-09T09:41:51.478153",
      "phase": "loading"
    },
    {
      "type": "event",
      "source": "Market Scanner",
      "event_type": "scan",
      "level": "INFO",
      "message": "\u2713 Data loaded for 5255/5405 tickers",
      "timestamp": "2026-01-09T09:56:15.459618"
    },
    {
      "type": "event",
      "source": "Market Scanner",
      "event_type": "scan",
      "level": "INFO",
      "message": "\ud83c\udfaf Scoring complete - Top 5: OSS (88), SMX (87), YCBD (87), AUGO (86), VELO (85)",
      "timestamp": "2026-01-09T09:56:23.947002"
    },
    {
      "type": "event",
      "source": "Market Scanner",
      "event_type": "scan",
      "level": "INFO",
      "message": "\ud83d\udfe1 Market Regime: UNKNOWN | Hot Sectors: Materials, Financials, Industrials",
      "timestamp": "2026-01-09T09:56:23.947735"
    },
    {
      "type": "event",
      "source": "Market Scanner",
      "event_type": "scan",
      "level": "INFO",
      "message": "\ud83d\udd04 12 rotation opportunities identified - avg score improvement: 40.1 points",
      "timestamp": "2026-01-09T09:56:24.621023"
    },
    {
      "type": "event",
      "source": "Market Scanner",
      "event_type": "scan",
      "level": "INFO",
      "message": "\ud83d\udd0d Daily Market Scan Started",
      "timestamp": "2026-01-09T09:56:39.490819",
      "phase": "start"
    },
    {
      "type": "event",
      "source": "Market Scanner",
      "event_type": "scan",
      "level": "INFO",
      "message": "\ud83d\udd0d Daily market scan initiated - analyzing 5405 tickers",
      "timestamp": "2026-01-09T09:56:39.490904"
    },
    {
      "type": "event",
      "source": "Market Scanner",
      "event_type": "scan",
      "level": "INFO",
      "message": "\ud83d\udcca Loading universe data (5405 tickers)",
      "timestamp": "2026-01-09T09:56:39.491062",
      "phase": "loading"
    },
    {
      "type": "event",
      "source": "Market Scanner",
      "event_type": "scan",
      "level": "INFO",
      "message": "\ud83d\udd0d Daily Market Scan Started",
      "timestamp": "2026-01-09T10:10:48.933642",
      "phase": "start"
    },
    {
      "type": "event",
      "source": "Market Scanner",
      "event_type": "scan",
      "level": "INFO",
      "message": "\ud83d\udd0d Daily market scan initiated - analyzing 5405 tickers",
      "timestamp": "2026-01-09T10:10:48.933712"
    },
    {
      "type": "event",
      "source": "Market Scanner",
      "event_type": "scan",
      "level": "INFO",
      "message": "\ud83d\udcca Loading universe data (5405 tickers)",
      "timestamp": "2026-01-09T10:10:48.933981",
      "phase": "loading"
    },
    {
      "type": "event",
      "source": "Market Scanner",
      "event_type": "scan",
      "level": "INFO",
      "message": "\ud83d\udd0d Daily Market Scan Started",
      "timestamp": "2026-01-09T10:12:13.690826",
      "phase": "start"
    },
    {
      "type": "event",
      "source": "Market Scanner",
      "event_type": "scan",
      "level": "INFO",
      "message": "\ud83d\udd0d Daily market scan initiated - analyzing 5405 tickers",
      "timestamp": "2026-01-09T10:12:13.690887"
    },
    {
      "type": "event",
      "source": "Market Scanner",
      "event_type": "scan",
      "level": "INFO",
      "message": "\ud83d\udcca Loading universe data (5405 tickers)",
      "timestamp": "2026-01-09T10:12:13.691147",
      "phase": "loading"
    },
    {
      "type": "event",
      "source": "Market Scanner",
      "event_type": "scan",
      "level": "INFO",
      "message": "\u2713 Data loaded for 5269/5405 tickers",
      "timestamp": "2026-01-09T10:22:57.590364"
    },
    {
      "type": "event",
      "source": "Market Scanner",
      "event_type": "scan",
      "level": "INFO",
      "message": "\ud83c\udfaf Scoring complete - Top 5: SMX (87), RKLX (86), YCBD (86), VELO (86), GLSI (85)",
      "timestamp": "2026-01-09T10:23:01.692167"
    },
    {
      "type": "event",
      "source": "Market Scanner",
      "event_type": "scan",
      "level": "INFO",
      "message": "\ud83d\udfe1 Market Regime: UNKNOWN | Hot Sectors: Materials, Industrials, Financials",
      "timestamp": "2026-01-09T10:23:01.692525"
    },
    {
      "type": "event",
      "source": "Market Scanner",
      "event_type": "scan",
      "level": "INFO",
      "message": "\ud83d\udd04 11 rotation opportunities identified - avg score improvement: 42.3 points",
      "timestamp": "2026-01-09T10:23:02.021562"
    },
    {
      "type": "event",
      "source": "Market Scanner",
      "event_type": "scan",
      "level": "INFO",
      "message": "\ud83d\udd0d Daily Market Scan Started",
      "timestamp": "2026-01-09T10:26:21.399712",
      "phase": "start"
    },
    {
      "type": "event",
      "source": "Market Scanner",
      "event_type": "scan",
      "level": "INFO",
      "message": "\ud83d\udd0d Daily market scan initiated - analyzing 5405 tickers",
      "timestamp": "2026-01-09T10:26:21.399741"
    },
    {
      "type": "event",
      "source": "Market Scanner",
      "event_type": "scan",
      "level": "INFO",
      "message": "\ud83d\udcca Loading universe data (5405 tickers)",
      "timestamp": "2026-01-09T10:26:21.399815",
      "phase": "loading"
    },
    {
      "type": "event",
      "source": "Market Scanner",
      "event_type": "scan",
      "level": "INFO",
      "message": "\ud83d\udd0d Daily Market Scan Started (TEST MODE)",
      "timestamp": "2026-01-09T10:28:08.433047",
      "phase": "start"
    },
    {
      "type": "event",
      "source": "Market Scanner",
      "event_type": "scan",
      "level": "INFO",
      "message": "\ud83d\udd0d Daily market scan initiated - analyzing 100 tickers",
      "timestamp": "2026-01-09T10:28:08.433376"
    },
    {
      "type": "event",
      "source": "Market Scanner",
      "event_type": "scan",
      "level": "INFO",
      "message": "\ud83d\udcca Loading universe data (100 tickers)",
      "timestamp": "2026-01-09T10:28:08.433453",
      "phase": "loading"
    },
    {
      "type": "event",
      "source": "Market Scanner",
      "event_type": "scan",
      "level": "INFO",
      "message": "\ud83d\udd0d Daily Market Scan Started (TEST MODE)",
      "timestamp": "2026-01-09T10:28:14.499028",
      "phase": "start"
    },
    {
      "type": "event",
      "source": "Market Scanner",
      "event_type": "scan",
      "level": "INFO",
      "message": "\ud83d\udd0d Daily market scan initiated - analyzing 100 tickers",
      "timestamp": "2026-01-09T10:28:14.499407"
    },
    {
      "type": "event",
      "source": "Market Scanner",
      "event_type": "scan",
      "level": "INFO",
      "message": "\ud83d\udcca Loading universe data (100 tickers)",
      "timestamp": "2026-01-09T10:28:14.499497",
      "phase": "loading"
    },
    {
      "type": "event",
      "source": "Market Scanner",
      "event_type": "scan",
      "level": "INFO",
      "message": "\u2713 Data loaded for 100/100 tickers",
      "timestamp": "2026-01-09T10:28:18.879412"
    },
    {
      "type": "event",
      "source": "Market Scanner",
      "event_type": "scan",
      "level": "INFO",
      "message": "\ud83c\udfaf Scoring complete - Top 5: KALV (79), PLTM (77), CTRI (77), TPR (75), YETI (72)",
      "timestamp": "2026-01-09T10:28:18.981042"
    },
    {
      "type": "event",
      "source": "Market Scanner",
      "event_type": "scan",
      "level": "INFO",
      "message": "\ud83d\udfe1 Market Regime: UNKNOWN | Hot Sectors: ",
      "timestamp": "2026-01-09T10:28:18.981133"
    },
    {
      "type": "event",
      "source": "Market Scanner",
      "event_type": "scan",
      "level": "INFO",
      "message": "\ud83d\udd04 22 rotation opportunities identified - avg score improvement: 57.4 points",
      "timestamp": "2026-01-09T10:28:19.130013"
    },
    {
      "type": "event",
      "source": "Market Scanner",
      "event_type": "scan",
      "level": "INFO",
      "message": "\u2713 Data loaded for 100/100 tickers",
      "timestamp": "2026-01-09T10:28:24.516960"
    },
    {
      "type": "event",
      "source": "Market Scanner",
      "event_type": "scan",
      "level": "INFO",
      "message": "\ud83c\udfaf Scoring complete - Top 5: PRAX (78), MUU (75), FOSL (73), EKSO (72), DAL (70)",
      "timestamp": "2026-01-09T10:28:24.626753"
    },
    {
      "type": "event",
      "source": "Market Scanner",
      "event_type": "scan",
      "level": "INFO",
      "message": "\ud83d\udfe1 Market Regime: UNKNOWN | Hot Sectors: ",
      "timestamp": "2026-01-09T10:28:24.626987"
    },
    {
      "type": "event",
      "source": "Market Scanner",
      "event_type": "scan",
      "level": "INFO",
      "message": "\ud83d\udd04 19 rotation opportunities identified - avg score improvement: 56.0 points",
      "timestamp": "2026-01-09T10:28:24.746286"
    },
    {
      "type": "event",
      "source": "Market Scanner",
      "event_type": "scan",
      "level": "INFO",
      "message": "\ud83d\udd0d Daily Market Scan Started (TEST MODE)",
      "timestamp": "2026-01-09T10:34:21.850949",
      "phase": "start"
    },
    {
      "type": "event",
      "source": "Market Scanner",
      "event_type": "scan",
      "level": "INFO",
      "message": "\ud83d\udd0d Daily market scan initiated - analyzing 100 tickers",
      "timestamp": "2026-01-09T10:34:21.851306"
    },
    {
      "type": "event",
      "source": "Market Scanner",
      "event_type": "scan",
      "level": "INFO",
      "message": "\ud83d\udcca Loading universe data (100 tickers)",
      "timestamp": "2026-01-09T10:34:21.851527",
      "phase": "loading"
    },
    {
      "type": "event",
      "source": "Market Scanner",
      "event_type": "scan",
      "level": "INFO",
      "message": "\ud83d\udd0d Daily Market Scan Started",
      "timestamp": "2026-01-09T11:05:39.486741",
      "phase": "start"
    },
    {
      "type": "event",
      "source": "Market Scanner",
      "event_type": "scan",
      "level": "INFO",
      "message": "\ud83d\udd0d Daily market scan initiated - analyzing 5405 tickers",
      "timestamp": "2026-01-09T11:05:39.486801"
    },
    {
      "type": "event",
      "source": "Market Scanner",
      "event_type": "scan",
      "level": "INFO",
      "message": "\ud83d\udcca Loading universe data (5405 tickers)",
      "timestamp": "2026-01-09T11:05:39.487037",
      "phase": "loading"
    },
    {
      "type": "event",
      "source": "Market Scanner",
      "event_type": "scan",
      "level": "INFO",
      "message": "\ud83d\udd0d Daily Market Scan Started",
      "timestamp": "2026-01-09T11:10:50.836080",
      "phase": "start"
    },
    {
      "type": "event",
      "source": "Market Scanner",
      "event_type": "scan",
      "level": "INFO",
      "message": "\ud83d\udd0d Daily market scan initiated - analyzing 5405 tickers",
      "timestamp": "2026-01-09T11:10:50.836144"
    },
    {
      "type": "event",
      "source": "Market Scanner",
      "event_type": "scan",
      "level": "INFO",
      "message": "\ud83d\udcca Loading universe data (5405 tickers)",
      "timestamp": "2026-01-09T11:10:50.836744",
      "phase": "loading"
    },
    {
      "type": "event",
      "source": "Market Scanner",
      "event_type": "scan",
      "level": "INFO",
      "message": "\ud83d\udd0d Daily Market Scan Started",
      "timestamp": "2026-01-09T11:30:11.424107",
      "phase": "start"
    },
    {
      "type": "event",
      "source": "Market Scanner",
      "event_type": "scan",
      "level": "INFO",
      "message": "\ud83d\udd0d Daily market scan initiated - analyzing 5405 tickers",
      "timestamp": "2026-01-09T11:30:11.424239"
    },
    {
      "type": "event",
      "source": "Market Scanner",
      "event_type": "scan",
      "level": "INFO",
      "message": "\ud83d\udcca Loading universe data (5405 tickers)",
      "timestamp": "2026-01-09T11:30:11.424736",
      "phase": "loading"
    },
    {
      "type": "event",
      "source": "Market Scanner",
      "event_type": "scan",
      "level": "INFO",
      "message": "\u2713 Data loaded for 5272/5405 tickers",
      "timestamp": "2026-01-09T11:38:36.102029"
    },
    {
      "type": "event",
      "source": "Market Scanner",
      "event_type": "scan",
      "level": "INFO",
      "message": "\ud83c\udfaf Scoring complete - Top 5: RKLX (88), SMX (88), OSS (87), YCBD (86), FLYT (86)",
      "timestamp": "2026-01-09T11:38:44.965538"
    },
    {
      "type": "event",
      "source": "Market Scanner",
      "event_type": "scan",
      "level": "INFO",
      "message": "\ud83d\udfe1 Market Regime: UNKNOWN | Hot Sectors: Materials, Industrials, Financials",
      "timestamp": "2026-01-09T11:38:44.966171"
    },
    {
      "type": "event",
      "source": "Market Scanner",
      "event_type": "scan",
      "level": "INFO",
      "message": "\ud83d\udd04 11 rotation opportunities identified - avg score improvement: 42.4 points",
      "timestamp": "2026-01-09T11:38:45.636890"
    },
    {
      "type": "event",
      "source": "Market Scanner",
      "event_type": "scan",
      "level": "INFO",
      "message": "\ud83d\udd0d Daily Market Scan Started",
      "timestamp": "2026-01-09T11:45:27.198391",
      "phase": "start"
    },
    {
      "type": "event",
      "source": "Market Scanner",
      "event_type": "scan",
      "level": "INFO",
      "message": "\ud83d\udd0d Daily market scan initiated - analyzing 5405 tickers",
      "timestamp": "2026-01-09T11:45:27.198497"
    },
    {
      "type": "event",
      "source": "Market Scanner",
      "event_type": "scan",
      "level": "INFO",
      "message": "\ud83d\udcca Loading universe data (5405 tickers)",
      "timestamp": "2026-01-09T11:45:27.199114",
      "phase": "loading"
    },
    {
      "type": "event",
      "source": "Profit Taker",
      "event_type": "portfolio",
      "level": "INFO",
      "message": "\ud83d\udc40 Monitoring 2 positions: QQQ -0.1%, SPY -0.1%",
      "timestamp": "2026-01-09T11:51:08.352109",
      "portfolio_value": "100K",
      "positions_count": 2,
      "avg_return": -0.1
    },
    {
      "type": "event",
      "source": "Profit Taker",
      "event_type": "portfolio",
      "level": "INFO",
      "message": "\ud83d\udc40 Monitoring 2 positions: QQQ -0.1%, SPY -0.1%",
      "timestamp": "2026-01-09T11:52:08.399355",
      "portfolio_value": "100K",
      "positions_count": 2,
      "avg_return": -0.1
    },
    {
      "type": "event",
      "source": "Profit Taker",
      "event_type": "portfolio",
      "level": "INFO",
      "message": "\ud83d\udc40 Monitoring 2 positions: QQQ -0.1%, SPY -0.1%",
      "timestamp": "2026-01-09T11:53:08.454510",
      "portfolio_value": "100K",
      "positions_count": 2,
      "avg_return": -0.1
    },
    {
      "type": "event",
      "source": "Market Scanner",
      "event_type": "scan",
      "level": "INFO",
      "message": "\ud83d\udd0d Daily Market Scan Started",
      "timestamp": "2026-01-09T11:54:01.421094",
      "phase": "start"
    },
    {
      "type": "event",
      "source": "Market Scanner",
      "event_type": "scan",
      "level": "INFO",
      "message": "\ud83d\udd0d Daily market scan initiated - analyzing 5405 tickers",
      "timestamp": "2026-01-09T11:54:01.421139"
    },
    {
      "type": "event",
      "source": "Market Scanner",
      "event_type": "scan",
      "level": "INFO",
      "message": "\ud83d\udcca Loading universe data (5405 tickers)",
      "timestamp": "2026-01-09T11:54:01.421381",
      "phase": "loading"
    },
    {
      "type": "event",
      "source": "Profit Taker",
      "event_type": "portfolio",
      "level": "INFO",
      "message": "\ud83d\udc40 Monitoring 2 positions: QQQ -0.1%, SPY +0.1%",
      "timestamp": "2026-01-09T11:55:01.251492",
      "portfolio_value": "100K",
      "positions_count": 2,
      "avg_return": 0.0
    },
    {
      "type": "event",
      "source": "Profit Taker",
      "event_type": "portfolio",
      "level": "INFO",
      "message": "\ud83d\udc40 Monitoring 2 positions: QQQ -0.1%, SPY -0.1%",
      "timestamp": "2026-01-09T11:56:01.339565",
      "portfolio_value": "100K",
      "positions_count": 2,
      "avg_return": -0.1
    },
    {
      "type": "event",
      "source": "Profit Taker",
      "event_type": "portfolio",
      "level": "INFO",
      "message": "\ud83d\udc40 Monitoring 2 positions: QQQ +0.1%, SPY -0.1%",
      "timestamp": "2026-01-09T11:57:01.381538",
      "portfolio_value": "100K",
      "positions_count": 2,
      "avg_return": 0.0
    },
    {
      "type": "event",
      "source": "Profit Taker",
      "event_type": "portfolio",
      "level": "INFO",
      "message": "\ud83d\udc40 Monitoring 2 positions: QQQ -0.1%, SPY -0.1%",
      "timestamp": "2026-01-09T11:58:01.453334",
      "portfolio_value": "100K",
      "positions_count": 2,
      "avg_return": -0.1
    },
    {
      "type": "event",
      "source": "Profit Taker",
      "event_type": "portfolio",
      "level": "INFO",
      "message": "\ud83d\udc40 Monitoring 2 positions: QQQ -0.1%, SPY +0.1%",
      "timestamp": "2026-01-09T11:59:01.509433",
      "portfolio_value": "100K",
      "positions_count": 2,
      "avg_return": -0.0
    },
    {
      "type": "event",
      "source": "Market Scanner",
      "event_type": "scan",
      "level": "INFO",
      "message": "\ud83d\udd0d Daily Market Scan Started",
      "timestamp": "2026-01-09T12:20:44.755809",
      "phase": "start"
    },
    {
      "type": "event",
      "source": "Market Scanner",
      "event_type": "scan",
      "level": "INFO",
      "message": "\ud83d\udd0d Daily market scan initiated - analyzing 5405 tickers",
      "timestamp": "2026-01-09T12:20:44.755844"
    },
    {
      "type": "event",
      "source": "Market Scanner",
      "event_type": "scan",
      "level": "INFO",
      "message": "\ud83d\udcca Loading universe data (5405 tickers)",
      "timestamp": "2026-01-09T12:20:44.756076",
      "phase": "loading"
    },
    {
      "type": "event",
      "source": "Profit Taker",
      "event_type": "portfolio",
      "level": "INFO",
      "message": "\ud83d\udc40 Monitoring 2 positions: QQQ +0.1%, SPY +0.1%",
      "timestamp": "2026-01-09T12:21:44.716634",
      "portfolio_value": "100K",
      "positions_count": 2,
      "avg_return": 0.1
    },
    {
      "type": "event",
      "source": "Profit Taker",
      "event_type": "portfolio",
      "level": "INFO",
      "message": "\ud83d\udc40 Monitoring 2 positions: QQQ +0.1%, SPY +0.1%",
      "timestamp": "2026-01-09T12:22:44.804909",
      "portfolio_value": "100K",
      "positions_count": 2,
      "avg_return": 0.1
    },
    {
      "type": "event",
      "source": "Profit Taker",
      "event_type": "portfolio",
      "level": "INFO",
      "message": "\ud83d\udc40 Monitoring 2 positions: QQQ +0.1%, SPY +0.1%",
      "timestamp": "2026-01-09T12:23:44.863679",
      "portfolio_value": "100K",
      "positions_count": 2,
      "avg_return": 0.1
    },
    {
      "type": "event",
      "source": "Profit Taker",
      "event_type": "portfolio",
      "level": "INFO",
      "message": "\ud83d\udc40 Monitoring 2 positions: QQQ +0.1%, SPY +0.1%",
      "timestamp": "2026-01-09T12:24:44.918271",
      "portfolio_value": "100K",
      "positions_count": 2,
      "avg_return": 0.1
    },
    {
      "type": "event",
      "source": "Profit Taker",
      "event_type": "portfolio",
      "level": "INFO",
      "message": "\ud83d\udc40 Monitoring 2 positions: QQQ +0.1%, SPY +0.1%",
      "timestamp": "2026-01-09T12:25:44.961868",
      "portfolio_value": "100K",
      "positions_count": 2,
      "avg_return": 0.1
    },
    {
      "type": "event",
      "source": "Market Scanner",
      "event_type": "scan",
      "level": "INFO",
      "message": "\ud83d\udd0d Daily Market Scan Started",
      "timestamp": "2026-01-09T12:30:37.138295",
      "phase": "start"
    },
    {
      "type": "event",
      "source": "Market Scanner",
      "event_type": "scan",
      "level": "INFO",
      "message": "\ud83d\udd0d Daily market scan initiated - analyzing 5405 tickers",
      "timestamp": "2026-01-09T12:30:37.138322"
    },
    {
      "type": "event",
      "source": "Market Scanner",
      "event_type": "scan",
      "level": "INFO",
      "message": "\ud83d\udcca Loading universe data (5405 tickers)",
      "timestamp": "2026-01-09T12:30:37.138497",
      "phase": "loading"
    },
    {
      "type": "event",
      "source": "Market Scanner",
      "event_type": "scan",
      "level": "INFO",
      "message": "\u2713 Data loaded for 5272/5405 tickers",
      "timestamp": "2026-01-09T12:37:39.333615"
    },
    {
      "type": "event",
      "source": "Market Scanner",
      "event_type": "scan",
      "level": "INFO",
      "message": "\ud83c\udfaf Scoring complete - Top 5: RKLX (89), OSS (89), SMX (88), FLYT (88), GLSI (87)",
      "timestamp": "2026-01-09T12:37:43.711674"
    },
    {
      "type": "event",
      "source": "Market Scanner",
      "event_type": "scan",
      "level": "INFO",
      "message": "\ud83d\udfe1 Market Regime: UNKNOWN | Hot Sectors: Materials, Industrials, Financials",
      "timestamp": "2026-01-09T12:37:43.712368"
    },
    {
      "type": "event",
      "source": "Market Scanner",
      "event_type": "scan",
      "level": "INFO",
      "message": "\ud83d\udd04 11 rotation opportunities identified - avg score improvement: 42.6 points",
      "timestamp": "2026-01-09T12:37:44.047049"
    },
    {
      "type": "event",
      "source": "Market Scanner",
      "event_type": "scan",
      "level": "INFO",
      "message": "\ud83d\udd0d Daily Market Scan Started",
      "timestamp": "2026-01-09T12:45:24.480968",
      "phase": "start"
    },
    {
      "type": "event",
      "source": "Market Scanner",
      "event_type": "scan",
      "level": "INFO",
      "message": "\ud83d\udd0d Daily market scan initiated - analyzing 5405 tickers",
      "timestamp": "2026-01-09T12:45:24.480999"
    },
    {
      "type": "event",
      "source": "Market Scanner",
      "event_type": "scan",
      "level": "INFO",
      "message": "\ud83d\udcca Loading universe data (5405 tickers)",
      "timestamp": "2026-01-09T12:45:24.481143",
      "phase": "loading"
    },
    {
      "type": "event",
      "source": "Market Scanner",
      "event_type": "scan",
      "level": "INFO",
      "message": "\u2713 Data loaded for 5272/5405 tickers",
      "timestamp": "2026-01-09T12:53:00.156024"
    },
    {
      "type": "event",
      "source": "Market Scanner",
      "event_type": "scan",
      "level": "INFO",
      "message": "\ud83c\udfaf Scoring complete - Top 5: OSS (90), RKLX (89), FLYT (88), SMX (88), GLSI (87)",
      "timestamp": "2026-01-09T12:53:04.204571"
    },
    {
      "type": "event",
      "source": "Market Scanner",
      "event_type": "scan",
      "level": "INFO",
      "message": "\ud83d\udfe1 Market Regime: UNKNOWN | Hot Sectors: Materials, Industrials, Financials",
      "timestamp": "2026-01-09T12:53:04.204959"
    },
    {
      "type": "event",
      "source": "Market Scanner",
      "event_type": "scan",
      "level": "INFO",
      "message": "\ud83d\udd04 11 rotation opportunities identified - avg score improvement: 42.2 points",
      "timestamp": "2026-01-09T12:53:04.541271"
    },
    {
      "type": "event",
      "source": "Market Scanner",
      "event_type": "scan",
      "level": "INFO",
      "message": "\ud83d\udd0d Daily Market Scan Started",
      "timestamp": "2026-01-09T13:00:14.964396",
      "phase": "start"
    },
    {
      "type": "event",
      "source": "Market Scanner",
      "event_type": "scan",
      "level": "INFO",
      "message": "\ud83d\udd0d Daily market scan initiated - analyzing 5405 tickers",
      "timestamp": "2026-01-09T13:00:14.964423"
    },
    {
      "type": "event",
      "source": "Market Scanner",
      "event_type": "scan",
      "level": "INFO",
      "message": "\ud83d\udcca Loading universe data (5405 tickers)",
      "timestamp": "2026-01-09T13:00:14.964643",
      "phase": "loading"
    }
  ]
}